[
    {
        "id": 1,
        "STR": "22",
        "STR_GAIN": "2.6",
        "STR_30": "97.4",
        "AGI": "23",
        "AGI_GAIN": "1.5",
        "AGI_30": "66.5",
        "INT": "18",
        "INT_GAIN": "2.0",
        "INT_30": "76",
        "TOTAL": "63",
        "TOTAL_GAIN": "6.1",
        "TOTAL_30": "239.9",
        "MS": "325",
        "ARMOR": "2.83",
        "DMG_MIN": "50",
        "DMG_MAX": "60",
        "RANGE": "150",
        "ATTACKSPEED": "120",
        "BAT": "1.7",
        "ATK_PT": "0.56",
        "ATK_BS": "0.41",
        "VIS_DAY": "1800",
        "VIS_NIGHT": "800",
        "TURNRATE": "0.6",
        "COLLISION": "24",
        "HP_SEC": "3.2",
        "LEGS": "2"
    },
    {
        "id": 2,
        "STR": "25",
        "STR_GAIN": "2.9",
        "STR_30": "109.1",
        "AGI": "22",
        "AGI_GAIN": "1.5",
        "AGI_30": "65.5",
        "INT": "25",
        "INT_GAIN": "1.8",
        "INT_30": "77.2",
        "TOTAL": "72",
        "TOTAL_GAIN": "6.2",
        "TOTAL_30": "251.8",
        "MS": "305",
        "ARMOR": "2.67",
        "DMG_MIN": "52",
        "DMG_MAX": "58",
        "RANGE": "150",
        "ATTACKSPEED": "100",
        "BAT": "1.7",
        "ATK_PT": "0.35",
        "ATK_BS": "0.65",
        "VIS_DAY": "1800",
        "VIS_NIGHT": "800",
        "TURNRATE": "0.6",
        "COLLISION": "24",
        "HP_SEC": "2.75",
        "LEGS": "2"
    },
    {
        "id": 3,
        "STR": "20",
        "STR_GAIN": "1.9",
        "STR_30": "75.1",
        "AGI": "20",
        "AGI_GAIN": "2.2",
        "AGI_30": "83.8",
        "INT": "23",
        "INT_GAIN": "3.4",
        "INT_30": "121.6",
        "TOTAL": "63",
        "TOTAL_GAIN": "7.5",
        "TOTAL_30": "280.5",
        "MS": "285",
        "ARMOR": "2.33",
        "DMG_MIN": "44",
        "DMG_MAX": "54",
        "RANGE": "675",
        "ATTACKSPEED": "100",
        "BAT": "1.7",
        "ATK_PT": "0.45",
        "ATK_BS": "0.3",
        "VIS_DAY": "1800",
        "VIS_NIGHT": "800",
        "TURNRATE": "0.6",
        "COLLISION": "24",
        "HP_SEC": "2.25",
        "LEGS": "0"
    },
    {
        "id": 4,
        "STR": "21",
        "STR_GAIN": "1.6",
        "STR_30": "67.4",
        "AGI": "24",
        "AGI_GAIN": "2.8",
        "AGI_30": "105.2",
        "INT": "12",
        "INT_GAIN": "1.8",
        "INT_30": "64.2",
        "TOTAL": "57",
        "TOTAL_GAIN": "6.2",
        "TOTAL_30": "236.8",
        "MS": "310",
        "ARMOR": "4",
        "DMG_MIN": "53",
        "DMG_MAX": "57",
        "RANGE": "150",
        "ATTACKSPEED": "100",
        "BAT": "1.4",
        "ATK_PT": "0.3",
        "ATK_BS": "0.6",
        "VIS_DAY": "1800",
        "VIS_NIGHT": "800",
        "TURNRATE": "0.6",
        "COLLISION": "24",
        "HP_SEC": "2.35",
        "LEGS": "2"
    },
    {
        "id": 5,
        "STR": "22",
        "STR_GAIN": "2.6",
        "STR_30": "97.4",
        "AGI": "20",
        "AGI_GAIN": "3.0",
        "AGI_30": "107",
        "INT": "24",
        "INT_GAIN": "2.6",
        "INT_30": "99.4",
        "TOTAL": "66",
        "TOTAL_GAIN": "8.2",
        "TOTAL_30": "303.8",
        "MS": "285",
        "ARMOR": "2.33",
        "DMG_MIN": "47",
        "DMG_MAX": "57",
        "RANGE": "625",
        "ATTACKSPEED": "100",
        "BAT": "1.7",
        "ATK_PT": "0.3",
        "ATK_BS": "0.7",
        "VIS_DAY": "1800",
        "VIS_NIGHT": "800",
        "TURNRATE": "0.7",
        "COLLISION": "24",
        "HP_SEC": "2.45",
        "LEGS": "2"
    },
    {
        "id": 6,
        "STR": "25",
        "STR_GAIN": "3.4",
        "STR_30": "123.6",
        "AGI": "20",
        "AGI_GAIN": "2.2",
        "AGI_30": "83.8",
        "INT": "18",
        "INT_GAIN": "1.6",
        "INT_30": "64.4",
        "TOTAL": "63",
        "TOTAL_GAIN": "7.2",
        "TOTAL_30": "271.8",
        "MS": "310",
        "ARMOR": "2.33",
        "DMG_MIN": "52",
        "DMG_MAX": "56",
        "RANGE": "150",
        "ATTACKSPEED": "100",
        "BAT": "1.7",
        "ATK_PT": "0.4",
        "ATK_BS": "0.5",
        "VIS_DAY": "1800",
        "VIS_NIGHT": "800",
        "TURNRATE": "0.6",
        "COLLISION": "24",
        "HP_SEC": "5.25",
        "LEGS": "2"
    },
    {
        "id": 7,
        "STR": "22",
        "STR_GAIN": "2.5",
        "STR_30": "94.5",
        "AGI": "22",
        "AGI_GAIN": "2.5",
        "AGI_30": "94.5",
        "INT": "22",
        "INT_GAIN": "2.5",
        "INT_30": "94.5",
        "TOTAL": "66",
        "TOTAL_GAIN": "7.5",
        "TOTAL_30": "283.5",
        "MS": "305",
        "ARMOR": "4.67",
        "DMG_MIN": "55",
        "DMG_MAX": "61",
        "RANGE": "400",
        "ATTACKSPEED": "100",
        "BAT": "1.7",
        "ATK_PT": "0.3",
        "ATK_BS": "0.7",
        "VIS_DAY": "1800",
        "VIS_NIGHT": "1200",
        "TURNRATE": "0.6",
        "COLLISION": "24",
        "HP_SEC": "2.45",
        "LEGS": "4"
    },
    {
        "id": 8,
        "STR": "28",
        "STR_GAIN": "2.9",
        "STR_30": "112.1",
        "AGI": "15",
        "AGI_GAIN": "1.8",
        "AGI_30": "67.2",
        "INT": "22",
        "INT_GAIN": "2.9",
        "INT_30": "106.1",
        "TOTAL": "65",
        "TOTAL_GAIN": "7.6",
        "TOTAL_30": "285.4",
        "MS": "310",
        "ARMOR": "4.5",
        "DMG_MIN": "39",
        "DMG_MAX": "43",
        "RANGE": "400",
        "ATTACKSPEED": "100",
        "BAT": "1.7",
        "ATK_PT": "0.3",
        "ATK_BS": "0.54",
        "VIS_DAY": "1600",
        "VIS_NIGHT": "800",
        "TURNRATE": "0.9",
        "COLLISION": "24",
        "HP_SEC": "4.55",
        "LEGS": "2"
    },
    {
        "id": 9,
        "STR": "23",
        "STR_GAIN": "2.9",
        "STR_30": "107.1",
        "AGI": "18",
        "AGI_GAIN": "1.6",
        "AGI_30": "64.4",
        "INT": "16",
        "INT_GAIN": "1.9",
        "INT_30": "71.1",
        "TOTAL": "57",
        "TOTAL_GAIN": "6.4",
        "TOTAL_30": "242.6",
        "MS": "305",
        "ARMOR": "3",
        "DMG_MIN": "54",
        "DMG_MAX": "58",
        "RANGE": "150",
        "ATTACKSPEED": "100",
        "BAT": "1.7",
        "ATK_PT": "0.3",
        "ATK_BS": "0.7",
        "VIS_DAY": "1800",
        "VIS_NIGHT": "800",
        "TURNRATE": "0.6",
        "COLLISION": "24",
        "HP_SEC": "2.55",
        "LEGS": "2"
    },
    {
        "id": 10,
        "STR": "24",
        "STR_GAIN": "2.7",
        "STR_30": "102.3",
        "AGI": "22",
        "AGI_GAIN": "3.1",
        "AGI_30": "111.9",
        "INT": "17",
        "INT_GAIN": "2.0",
        "INT_30": "75",
        "TOTAL": "63",
        "TOTAL_GAIN": "7.8",
        "TOTAL_30": "289.2",
        "MS": "300",
        "ARMOR": "5.67",
        "DMG_MIN": "57",
        "DMG_MAX": "63",
        "RANGE": "150",
        "ATTACKSPEED": "100",
        "BAT": "1.7",
        "ATK_PT": "0.43",
        "ATK_BS": "0.74",
        "VIS_DAY": "1800",
        "VIS_NIGHT": "800",
        "TURNRATE": "0.6",
        "COLLISION": "24",
        "HP_SEC": "2.65",
        "LEGS": "2"
    },
    {
        "id": 11,
        "STR": "20",
        "STR_GAIN": "2.5",
        "STR_30": "92.5",
        "AGI": "21",
        "AGI_GAIN": "2.6",
        "AGI_30": "96.4",
        "INT": "22",
        "INT_GAIN": "1.9",
        "INT_30": "77.1",
        "TOTAL": "63",
        "TOTAL_GAIN": "7.0",
        "TOTAL_30": "266",
        "MS": "325",
        "ARMOR": "7.5",
        "DMG_MIN": "51",
        "DMG_MAX": "59",
        "RANGE": "150",
        "ATTACKSPEED": "100",
        "BAT": "1.7",
        "ATK_PT": "0.59",
        "ATK_BS": "0.59",
        "VIS_DAY": "1800",
        "VIS_NIGHT": "1000",
        "TURNRATE": "0.6",
        "COLLISION": "24",
        "HP_SEC": "3.25",
        "LEGS": "2"
    },
    {
        "id": 12,
        "STR": "23",
        "STR_GAIN": "3.7",
        "STR_30": "130.3",
        "AGI": "19",
        "AGI_GAIN": "2.0",
        "AGI_30": "77",
        "INT": "15",
        "INT_GAIN": "1.6",
        "INT_30": "61.4",
        "TOTAL": "57",
        "TOTAL_GAIN": "7.3",
        "TOTAL_30": "268.7",
        "MS": "310",
        "ARMOR": "2.17",
        "DMG_MIN": "52",
        "DMG_MAX": "59",
        "RANGE": "150",
        "ATTACKSPEED": "100",
        "BAT": "1.7",
        "ATK_PT": "0.35",
        "ATK_BS": "0.65",
        "VIS_DAY": "1800",
        "VIS_NIGHT": "800",
        "TURNRATE": "0.6",
        "COLLISION": "24",
        "HP_SEC": "2.8",
        "LEGS": "2"
    },
    {
        "id": 13,
        "STR": "22",
        "STR_GAIN": "2.5",
        "STR_30": "94.5",
        "AGI": "17",
        "AGI_GAIN": "1.8",
        "AGI_30": "69.2",
        "INT": "14",
        "INT_GAIN": "2.8",
        "INT_30": "95.2",
        "TOTAL": "53",
        "TOTAL_GAIN": "7.1",
        "TOTAL_30": "258.9",
        "MS": "295",
        "ARMOR": "3.83",
        "DMG_MIN": "52",
        "DMG_MAX": "58",
        "RANGE": "150",
        "ATTACKSPEED": "100",
        "BAT": "1.8",
        "ATK_PT": "0.3",
        "ATK_BS": "0.3",
        "VIS_DAY": "1800",
        "VIS_NIGHT": "800",
        "TURNRATE": "0.9",
        "COLLISION": "24",
        "HP_SEC": "2.45",
        "LEGS": "2"
    },
    {
        "id": 14,
        "STR": "18",
        "STR_GAIN": "3.2",
        "STR_30": "110.8",
        "AGI": "19",
        "AGI_GAIN": "3.4",
        "AGI_30": "117.6",
        "INT": "18",
        "INT_GAIN": "2.0",
        "INT_30": "76",
        "TOTAL": "55",
        "TOTAL_GAIN": "8.6",
        "TOTAL_30": "304.4",
        "MS": "280",
        "ARMOR": "3.17",
        "DMG_MIN": "48",
        "DMG_MAX": "54",
        "RANGE": "150",
        "ATTACKSPEED": "125",
        "BAT": "1.7",
        "ATK_PT": "0.4",
        "ATK_BS": "0.5",
        "VIS_DAY": "1800",
        "VIS_NIGHT": "800",
        "TURNRATE": "0.6",
        "COLLISION": "24",
        "HP_SEC": "2.05",
        "LEGS": "8"
    },
    {
        "id": 15,
        "STR": "27",
        "STR_GAIN": "4.0",
        "STR_30": "143",
        "AGI": "15",
        "AGI_GAIN": "1.0",
        "AGI_30": "44",
        "INT": "15",
        "INT_GAIN": "1.6",
        "INT_30": "61.4",
        "TOTAL": "57",
        "TOTAL_GAIN": "6.6",
        "TOTAL_30": "248.4",
        "MS": "300",
        "ARMOR": "3.5",
        "DMG_MIN": "63",
        "DMG_MAX": "65",
        "RANGE": "150",
        "ATTACKSPEED": "90",
        "BAT": "1.7",
        "ATK_PT": "0.3",
        "ATK_BS": "0.3",
        "VIS_DAY": "1800",
        "VIS_NIGHT": "800",
        "TURNRATE": "0.6",
        "COLLISION": "24",
        "HP_SEC": "2.95",
        "LEGS": "4"
    },
    {
        "id": 16,
        "STR": "22",
        "STR_GAIN": "3.2",
        "STR_30": "114.8",
        "AGI": "18",
        "AGI_GAIN": "1.4",
        "AGI_30": "58.6",
        "INT": "18",
        "INT_GAIN": "1.2",
        "INT_30": "52.8",
        "TOTAL": "58",
        "TOTAL_GAIN": "5.8",
        "TOTAL_30": "226.2",
        "MS": "325",
        "ARMOR": "5",
        "DMG_MIN": "51",
        "DMG_MAX": "81",
        "RANGE": "150",
        "ATTACKSPEED": "100",
        "BAT": "1.7",
        "ATK_PT": "0.5",
        "ATK_BS": "0.5",
        "VIS_DAY": "1800",
        "VIS_NIGHT": "800",
        "TURNRATE": "0.6",
        "COLLISION": "24",
        "HP_SEC": "2.45",
        "LEGS": "2"
    },
    {
        "id": 17,
        "STR": "25",
        "STR_GAIN": "2.0",
        "STR_30": "83",
        "AGI": "15",
        "AGI_GAIN": "2.1",
        "AGI_30": "75.9",
        "INT": "19",
        "INT_GAIN": "3.2",
        "INT_30": "111.8",
        "TOTAL": "59",
        "TOTAL_GAIN": "7.3",
        "TOTAL_30": "270.7",
        "MS": "300",
        "ARMOR": "1.5",
        "DMG_MIN": "46",
        "DMG_MAX": "56",
        "RANGE": "650",
        "ATTACKSPEED": "100",
        "BAT": "1.7",
        "ATK_PT": "0.5",
        "ATK_BS": "0.5",
        "VIS_DAY": "1800",
        "VIS_NIGHT": "800",
        "TURNRATE": "0.6",
        "COLLISION": "24",
        "HP_SEC": "2.75",
        "LEGS": "2"
    },
    {
        "id": 18,
        "STR": "16",
        "STR_GAIN": "2.0",
        "STR_30": "74",
        "AGI": "22",
        "AGI_GAIN": "2.5",
        "AGI_30": "94.5",
        "INT": "18",
        "INT_GAIN": "2.2",
        "INT_30": "81.8",
        "TOTAL": "56",
        "TOTAL_GAIN": "6.7",
        "TOTAL_30": "250.3",
        "MS": "290",
        "ARMOR": "3.67",
        "DMG_MIN": "37",
        "DMG_MAX": "43",
        "RANGE": "600",
        "ATTACKSPEED": "100",
        "BAT": "1.7",
        "ATK_PT": "0.4",
        "ATK_BS": "0.3",
        "VIS_DAY": "1800",
        "VIS_NIGHT": "800",
        "TURNRATE": "0.6",
        "COLLISION": "24",
        "HP_SEC": "1.85",
        "LEGS": "2"
    },
    {
        "id": 19,
        "STR": "26",
        "STR_GAIN": "3.5",
        "STR_30": "127.5",
        "AGI": "13",
        "AGI_GAIN": "2.3",
        "AGI_30": "79.7",
        "INT": "18",
        "INT_GAIN": "1.5",
        "INT_30": "61.5",
        "TOTAL": "57",
        "TOTAL_GAIN": "7.3",
        "TOTAL_30": "268.7",
        "MS": "310",
        "ARMOR": "3.17",
        "DMG_MIN": "50",
        "DMG_MAX": "52",
        "RANGE": "150",
        "ATTACKSPEED": "100",
        "BAT": "1.7",
        "ATK_PT": "0.33",
        "ATK_BS": "0.64",
        "VIS_DAY": "1800",
        "VIS_NIGHT": "800",
        "TURNRATE": "0.6",
        "COLLISION": "24",
        "HP_SEC": "2.85",
        "LEGS": "2"
    },
    {
        "id": 20,
        "STR": "18",
        "STR_GAIN": "2.2",
        "STR_30": "81.8",
        "AGI": "16",
        "AGI_GAIN": "1.6",
        "AGI_30": "62.4",
        "INT": "16",
        "INT_GAIN": "3.3",
        "INT_30": "111.7",
        "TOTAL": "50",
        "TOTAL_GAIN": "7.1",
        "TOTAL_30": "255.9",
        "MS": "280",
        "ARMOR": "1.67",
        "DMG_MIN": "44",
        "DMG_MAX": "50",
        "RANGE": "600",
        "ATTACKSPEED": "100",
        "BAT": "1.7",
        "ATK_PT": "0.45",
        "ATK_BS": "0",
        "VIS_DAY": "1800",
        "VIS_NIGHT": "800",
        "TURNRATE": "0.6",
        "COLLISION": "24",
        "HP_SEC": "2.05",
        "LEGS": "2"
    },
    {
        "id": 21,
        "STR": "22",
        "STR_GAIN": "2.6",
        "STR_30": "97.4",
        "AGI": "18",
        "AGI_GAIN": "1.8",
        "AGI_30": "70.2",
        "INT": "21",
        "INT_GAIN": "2.7",
        "INT_30": "99.3",
        "TOTAL": "61",
        "TOTAL_GAIN": "7.1",
        "TOTAL_30": "266.9",
        "MS": "295",
        "ARMOR": "5",
        "DMG_MIN": "54",
        "DMG_MAX": "60",
        "RANGE": "150",
        "ATTACKSPEED": "100",
        "BAT": "1.7",
        "ATK_PT": "0.59",
        "ATK_BS": "0.58",
        "VIS_DAY": "1800",
        "VIS_NIGHT": "800",
        "TURNRATE": "0.6",
        "COLLISION": "24",
        "HP_SEC": "2.45",
        "LEGS": "2"
    },
    {
        "id": 22,
        "STR": "20",
        "STR_GAIN": "2.0",
        "STR_30": "78",
        "AGI": "18",
        "AGI_GAIN": "1.6",
        "AGI_30": "64.4",
        "INT": "21",
        "INT_GAIN": "3.5",
        "INT_30": "122.5",
        "TOTAL": "59",
        "TOTAL_GAIN": "7.1",
        "TOTAL_30": "264.9",
        "MS": "290",
        "ARMOR": "2",
        "DMG_MIN": "48",
        "DMG_MAX": "56",
        "RANGE": "475",
        "ATTACKSPEED": "115",
        "BAT": "1.5",
        "ATK_PT": "0.3",
        "ATK_BS": "1",
        "VIS_DAY": "1800",
        "VIS_NIGHT": "800",
        "TURNRATE": "0.7",
        "COLLISION": "24",
        "HP_SEC": "2.75",
        "LEGS": "2"
    },
    {
        "id": 23,
        "STR": "26",
        "STR_GAIN": "3.6",
        "STR_30": "130.4",
        "AGI": "14",
        "AGI_GAIN": "1.7",
        "AGI_30": "63.3",
        "INT": "20",
        "INT_GAIN": "2.2",
        "INT_30": "83.8",
        "TOTAL": "60",
        "TOTAL_GAIN": "7.5",
        "TOTAL_30": "277.5",
        "MS": "310",
        "ARMOR": "4.33",
        "DMG_MIN": "57",
        "DMG_MAX": "61",
        "RANGE": "150",
        "ATTACKSPEED": "100",
        "BAT": "1.7",
        "ATK_PT": "0.46",
        "ATK_BS": "0",
        "VIS_DAY": "1800",
        "VIS_NIGHT": "800",
        "TURNRATE": "0.6",
        "COLLISION": "24",
        "HP_SEC": "2.85",
        "LEGS": "2"
    },
    {
        "id": 24,
        "STR": "18",
        "STR_GAIN": "2.3",
        "STR_30": "84.7",
        "AGI": "20",
        "AGI_GAIN": "1.7",
        "AGI_30": "69.3",
        "INT": "25",
        "INT_GAIN": "3.7",
        "INT_30": "132.3",
        "TOTAL": "63",
        "TOTAL_GAIN": "7.7",
        "TOTAL_30": "286.3",
        "MS": "305",
        "ARMOR": "3.33",
        "DMG_MIN": "47",
        "DMG_MAX": "53",
        "RANGE": "575",
        "ATTACKSPEED": "100",
        "BAT": "1.7",
        "ATK_PT": "0.3",
        "ATK_BS": "0.3",
        "VIS_DAY": "1800",
        "VIS_NIGHT": "800",
        "TURNRATE": "0.7",
        "COLLISION": "24",
        "HP_SEC": "2.05",
        "LEGS": "2"
    },
    {
        "id": 25,
        "STR": "21",
        "STR_GAIN": "3.1",
        "STR_30": "110.9",
        "AGI": "14",
        "AGI_GAIN": "1.8",
        "AGI_30": "66.2",
        "INT": "24",
        "INT_GAIN": "3.3",
        "INT_30": "119.7",
        "TOTAL": "59",
        "TOTAL_GAIN": "8.2",
        "TOTAL_30": "296.8",
        "MS": "325",
        "ARMOR": "3.33",
        "DMG_MIN": "47",
        "DMG_MAX": "57",
        "RANGE": "600",
        "ATTACKSPEED": "100",
        "BAT": "1.7",
        "ATK_PT": "0.5",
        "ATK_BS": "0.51",
        "VIS_DAY": "1800",
        "VIS_NIGHT": "800",
        "TURNRATE": "0.8",
        "COLLISION": "24",
        "HP_SEC": "2.35",
        "LEGS": "2"
    },
    {
        "id": 26,
        "STR": "21",
        "STR_GAIN": "2.4",
        "STR_30": "90.6",
        "AGI": "15",
        "AGI_GAIN": "1.4",
        "AGI_30": "55.6",
        "INT": "20",
        "INT_GAIN": "2.9",
        "INT_30": "104.1",
        "TOTAL": "56",
        "TOTAL_GAIN": "6.7",
        "TOTAL_30": "250.3",
        "MS": "295",
        "ARMOR": "2.5",
        "DMG_MIN": "49",
        "DMG_MAX": "53",
        "RANGE": "625",
        "ATTACKSPEED": "100",
        "BAT": "1.7",
        "ATK_PT": "0.4",
        "ATK_BS": "0.5",
        "VIS_DAY": "1800",
        "VIS_NIGHT": "800",
        "TURNRATE": "0.6",
        "COLLISION": "24",
        "HP_SEC": "2.35",
        "LEGS": "2"
    },
    {
        "id": 27,
        "STR": "24",
        "STR_GAIN": "3.7",
        "STR_30": "131.3",
        "AGI": "11",
        "AGI_GAIN": "0.9",
        "AGI_30": "37.1",
        "INT": "15",
        "INT_GAIN": "1.7",
        "INT_30": "64.3",
        "TOTAL": "50",
        "TOTAL_GAIN": "6.3",
        "TOTAL_30": "232.7",
        "MS": "285",
        "ARMOR": "4.83",
        "DMG_MIN": "58",
        "DMG_MAX": "68",
        "RANGE": "200",
        "ATTACKSPEED": "100",
        "BAT": "1.9",
        "ATK_PT": "0.5",
        "ATK_BS": "0.7",
        "VIS_DAY": "1800",
        "VIS_NIGHT": "800",
        "TURNRATE": "0.6",
        "COLLISION": "24",
        "HP_SEC": "2.65",
        "LEGS": "2"
    },
    {
        "id": 28,
        "STR": "21",
        "STR_GAIN": "3.4",
        "STR_30": "119.6",
        "AGI": "19",
        "AGI_GAIN": "2.0",
        "AGI_30": "77",
        "INT": "18",
        "INT_GAIN": "1.7",
        "INT_30": "67.3",
        "TOTAL": "58",
        "TOTAL_GAIN": "7.1",
        "TOTAL_30": "263.9",
        "MS": "310",
        "ARMOR": "3.17",
        "DMG_MIN": "53",
        "DMG_MAX": "59",
        "RANGE": "150",
        "ATTACKSPEED": "100",
        "BAT": "1.7",
        "ATK_PT": "0.5",
        "ATK_BS": "0.5",
        "VIS_DAY": "1800",
        "VIS_NIGHT": "800",
        "TURNRATE": "0.6",
        "COLLISION": "24",
        "HP_SEC": "2.35",
        "LEGS": "2"
    },
    {
        "id": 29,
        "STR": "16",
        "STR_GAIN": "1.9",
        "STR_30": "71.1",
        "AGI": "20",
        "AGI_GAIN": "2.9",
        "AGI_30": "104.1",
        "INT": "15",
        "INT_GAIN": "1.4",
        "INT_30": "55.6",
        "TOTAL": "51",
        "TOTAL_GAIN": "6.2",
        "TOTAL_30": "230.8",
        "MS": "295",
        "ARMOR": "3.33",
        "DMG_MIN": "49",
        "DMG_MAX": "56",
        "RANGE": "625",
        "ATTACKSPEED": "100",
        "BAT": "1.7",
        "ATK_PT": "0.5",
        "ATK_BS": "0.3",
        "VIS_DAY": "1800",
        "VIS_NIGHT": "800",
        "TURNRATE": "0.7",
        "COLLISION": "24",
        "HP_SEC": "1.85",
        "LEGS": "2"
    },
    {
        "id": 30,
        "STR": "22",
        "STR_GAIN": "3.8",
        "STR_30": "132.2",
        "AGI": "17",
        "AGI_GAIN": "2.4",
        "AGI_30": "86.6",
        "INT": "20",
        "INT_GAIN": "2.1",
        "INT_30": "80.9",
        "TOTAL": "59",
        "TOTAL_GAIN": "8.3",
        "TOTAL_30": "299.7",
        "MS": "290",
        "ARMOR": "2.83",
        "DMG_MIN": "47",
        "DMG_MAX": "57",
        "RANGE": "150",
        "ATTACKSPEED": "100",
        "BAT": "1.7",
        "ATK_PT": "0.35",
        "ATK_BS": "0.65",
        "VIS_DAY": "1800",
        "VIS_NIGHT": "800",
        "TURNRATE": "0.6",
        "COLLISION": "24",
        "HP_SEC": "3.2",
        "LEGS": "2"
    },
    {
        "id": 31,
        "STR": "22",
        "STR_GAIN": "3.7",
        "STR_30": "129.3",
        "AGI": "12",
        "AGI_GAIN": "1.4",
        "AGI_30": "52.6",
        "INT": "18",
        "INT_GAIN": "2.1",
        "INT_30": "78.9",
        "TOTAL": "52",
        "TOTAL_GAIN": "7.2",
        "TOTAL_30": "260.8",
        "MS": "315",
        "ARMOR": "4",
        "DMG_MIN": "49",
        "DMG_MAX": "59",
        "RANGE": "150",
        "ATTACKSPEED": "100",
        "BAT": "1.7",
        "ATK_PT": "0.467",
        "ATK_BS": "0.863",
        "VIS_DAY": "1800",
        "VIS_NIGHT": "800",
        "TURNRATE": "0.9",
        "COLLISION": "24",
        "HP_SEC": "3.2",
        "LEGS": "2"
    },
    {
        "id": 32,
        "STR": "26",
        "STR_GAIN": "3.0",
        "STR_30": "113",
        "AGI": "14",
        "AGI_GAIN": "1.8",
        "AGI_30": "66.2",
        "INT": "23",
        "INT_GAIN": "1.6",
        "INT_30": "69.4",
        "TOTAL": "63",
        "TOTAL_GAIN": "6.4",
        "TOTAL_30": "248.6",
        "MS": "310",
        "ARMOR": "2.33",
        "DMG_MIN": "49",
        "DMG_MAX": "59",
        "RANGE": "150",
        "ATTACKSPEED": "100",
        "BAT": "1.7",
        "ATK_PT": "0.35",
        "ATK_BS": "0.97",
        "VIS_DAY": "1800",
        "VIS_NIGHT": "800",
        "TURNRATE": "0.6",
        "COLLISION": "24",
        "HP_SEC": "2.85",
        "LEGS": "2"
    },
    {
        "id": 33,
        "STR": "21",
        "STR_GAIN": "2.6",
        "STR_30": "96.4",
        "AGI": "22",
        "AGI_GAIN": "2.9",
        "AGI_30": "106.1",
        "INT": "20",
        "INT_GAIN": "2.2",
        "INT_30": "83.8",
        "TOTAL": "63",
        "TOTAL_GAIN": "7.7",
        "TOTAL_30": "286.3",
        "MS": "305",
        "ARMOR": "2.67",
        "DMG_MIN": "55",
        "DMG_MAX": "59",
        "RANGE": "150",
        "ATTACKSPEED": "100",
        "BAT": "1.7",
        "ATK_PT": "0.4",
        "ATK_BS": "0.3",
        "VIS_DAY": "1800",
        "VIS_NIGHT": "800",
        "TURNRATE": "0.6",
        "COLLISION": "24",
        "HP_SEC": "2.85",
        "LEGS": "2"
    },
    {
        "id": 34,
        "STR": "17",
        "STR_GAIN": "1.7",
        "STR_30": "66.3",
        "AGI": "19",
        "AGI_GAIN": "2.1",
        "AGI_30": "79.9",
        "INT": "22",
        "INT_GAIN": "3.8",
        "INT_30": "132.2",
        "TOTAL": "58",
        "TOTAL_GAIN": "7.6",
        "TOTAL_30": "278.4",
        "MS": "320",
        "ARMOR": "4.17",
        "DMG_MIN": "45",
        "DMG_MAX": "55",
        "RANGE": "575",
        "ATTACKSPEED": "100",
        "BAT": "1.7",
        "ATK_PT": "0.3",
        "ATK_BS": "0.7",
        "VIS_DAY": "1800",
        "VIS_NIGHT": "800",
        "TURNRATE": "0.6",
        "COLLISION": "24",
        "HP_SEC": "1.95",
        "LEGS": "4"
    },
    {
        "id": 35,
        "STR": "21",
        "STR_GAIN": "2.5",
        "STR_30": "93.5",
        "AGI": "14",
        "AGI_GAIN": "1.0",
        "AGI_30": "43",
        "INT": "19",
        "INT_GAIN": "3.6",
        "INT_30": "123.4",
        "TOTAL": "54",
        "TOTAL_GAIN": "7.1",
        "TOTAL_30": "259.9",
        "MS": "290",
        "ARMOR": "4.33",
        "DMG_MIN": "43",
        "DMG_MAX": "49",
        "RANGE": "500",
        "ATTACKSPEED": "100",
        "BAT": "1.7",
        "ATK_PT": "0.4",
        "ATK_BS": "0.77",
        "VIS_DAY": "1800",
        "VIS_NIGHT": "800",
        "TURNRATE": "0.6",
        "COLLISION": "24",
        "HP_SEC": "2.35",
        "LEGS": "0"
    },
    {
        "id": 36,
        "STR": "20",
        "STR_GAIN": "2.4",
        "STR_30": "89.6",
        "AGI": "19",
        "AGI_GAIN": "3.0",
        "AGI_30": "106",
        "INT": "15",
        "INT_GAIN": "1.5",
        "INT_30": "58.5",
        "TOTAL": "54",
        "TOTAL_GAIN": "6.9",
        "TOTAL_30": "254.1",
        "MS": "300",
        "ARMOR": "4.17",
        "DMG_MIN": "56",
        "DMG_MAX": "62",
        "RANGE": "150",
        "ATTACKSPEED": "100",
        "BAT": "1.7",
        "ATK_PT": "0.5",
        "ATK_BS": "0.56",
        "VIS_DAY": "1800",
        "VIS_NIGHT": "800",
        "TURNRATE": "0.9",
        "COLLISION": "24",
        "HP_SEC": "3",
        "LEGS": "2"
    },
    {
        "id": 37,
        "STR": "21",
        "STR_GAIN": "2.4",
        "STR_30": "90.6",
        "AGI": "18",
        "AGI_GAIN": "1.9",
        "AGI_30": "73.1",
        "INT": "25",
        "INT_GAIN": "3.8",
        "INT_30": "135.2",
        "TOTAL": "64",
        "TOTAL_GAIN": "8.1",
        "TOTAL_30": "298.9",
        "MS": "290",
        "ARMOR": "3",
        "DMG_MIN": "46",
        "DMG_MAX": "50",
        "RANGE": "600",
        "ATTACKSPEED": "100",
        "BAT": "1.7",
        "ATK_PT": "0.35",
        "ATK_BS": "0.85",
        "VIS_DAY": "1800",
        "VIS_NIGHT": "800",
        "TURNRATE": "0.6",
        "COLLISION": "24",
        "HP_SEC": "2.35",
        "LEGS": "0"
    },
    {
        "id": 38,
        "STR": "22",
        "STR_GAIN": "2.5",
        "STR_30": "94.5",
        "AGI": "26",
        "AGI_GAIN": "3.3",
        "AGI_30": "121.7",
        "INT": "21",
        "INT_GAIN": "2.4",
        "INT_30": "90.6",
        "TOTAL": "69",
        "TOTAL_GAIN": "8.2",
        "TOTAL_30": "306.8",
        "MS": "315",
        "ARMOR": "6.33",
        "DMG_MIN": "42",
        "DMG_MAX": "48",
        "RANGE": "365",
        "ATTACKSPEED": "125",
        "BAT": "1.7",
        "ATK_PT": "0.2",
        "ATK_BS": "0.1",
        "VIS_DAY": "1800",
        "VIS_NIGHT": "800",
        "TURNRATE": "0.6",
        "COLLISION": "24",
        "HP_SEC": "2.45",
        "LEGS": "2"
    },
    {
        "id": 39,
        "STR": "17",
        "STR_GAIN": "2.0",
        "STR_30": "75",
        "AGI": "24",
        "AGI_GAIN": "3.6",
        "AGI_30": "128.4",
        "INT": "21",
        "INT_GAIN": "2.9",
        "INT_30": "105.1",
        "TOTAL": "62",
        "TOTAL_GAIN": "8.5",
        "TOTAL_30": "308.5",
        "MS": "310",
        "ARMOR": "4",
        "DMG_MIN": "46",
        "DMG_MAX": "53",
        "RANGE": "575",
        "ATTACKSPEED": "100",
        "BAT": "2",
        "ATK_PT": "0.4",
        "ATK_BS": "1.5",
        "VIS_DAY": "1800",
        "VIS_NIGHT": "800",
        "TURNRATE": "0.9",
        "COLLISION": "8",
        "HP_SEC": "1.95",
        "LEGS": "4"
    },
    {
        "id": 40,
        "STR": "20",
        "STR_GAIN": "3.3",
        "STR_30": "115.7",
        "AGI": "10",
        "AGI_GAIN": "1.5",
        "AGI_30": "53.5",
        "INT": "18",
        "INT_GAIN": "1.5",
        "INT_30": "61.5",
        "TOTAL": "48",
        "TOTAL_GAIN": "6.3",
        "TOTAL_30": "230.7",
        "MS": "295",
        "ARMOR": "0.67",
        "DMG_MIN": "41",
        "DMG_MAX": "46",
        "RANGE": "400",
        "ATTACKSPEED": "100",
        "BAT": "1.6",
        "ATK_PT": "0.3",
        "ATK_BS": "0.5",
        "VIS_DAY": "1800",
        "VIS_NIGHT": "800",
        "TURNRATE": "0.6",
        "COLLISION": "24",
        "HP_SEC": "2.25",
        "LEGS": "2"
    },
    {
        "id": 41,
        "STR": "18",
        "STR_GAIN": "2.4",
        "STR_30": "87.6",
        "AGI": "14",
        "AGI_GAIN": "1.9",
        "AGI_30": "69.1",
        "INT": "15",
        "INT_GAIN": "4.6",
        "INT_30": "148.4",
        "TOTAL": "47",
        "TOTAL_GAIN": "8.9",
        "TOTAL_30": "305.1",
        "MS": "285",
        "ARMOR": "2.33",
        "DMG_MIN": "44",
        "DMG_MAX": "50",
        "RANGE": "600",
        "ATTACKSPEED": "100",
        "BAT": "1.7",
        "ATK_PT": "0.4",
        "ATK_BS": "0.7",
        "VIS_DAY": "1800",
        "VIS_NIGHT": "800",
        "TURNRATE": "0.6",
        "COLLISION": "24",
        "HP_SEC": "2.05",
        "LEGS": "2"
    },
    {
        "id": 42,
        "STR": "17",
        "STR_GAIN": "3.0",
        "STR_30": "104",
        "AGI": "14",
        "AGI_GAIN": "1.6",
        "AGI_30": "60.4",
        "INT": "23",
        "INT_GAIN": "1.7",
        "INT_30": "72.3",
        "TOTAL": "54",
        "TOTAL_GAIN": "6.3",
        "TOTAL_30": "236.7",
        "MS": "320",
        "ARMOR": "3.33",
        "DMG_MIN": "45",
        "DMG_MAX": "51",
        "RANGE": "500",
        "ATTACKSPEED": "100",
        "BAT": "1.7",
        "ATK_PT": "0.3",
        "ATK_BS": "0.4",
        "VIS_DAY": "1800",
        "VIS_NIGHT": "800",
        "TURNRATE": "0.7",
        "COLLISION": "24",
        "HP_SEC": "1.95",
        "LEGS": "0"
    },
    {
        "id": 43,
        "STR": "25",
        "STR_GAIN": "2.8",
        "STR_30": "106.2",
        "AGI": "15",
        "AGI_GAIN": "1.2",
        "AGI_30": "49.8",
        "INT": "26",
        "INT_GAIN": "3.0",
        "INT_30": "113",
        "TOTAL": "66",
        "TOTAL_GAIN": "7.0",
        "TOTAL_30": "269",
        "MS": "290",
        "ARMOR": "3.5",
        "DMG_MIN": "53",
        "DMG_MAX": "61",
        "RANGE": "400",
        "ATTACKSPEED": "100",
        "BAT": "1.7",
        "ATK_PT": "0.4",
        "ATK_BS": "0.3",
        "VIS_DAY": "1800",
        "VIS_NIGHT": "800",
        "TURNRATE": "0.6",
        "COLLISION": "24",
        "HP_SEC": "2.75",
        "LEGS": "2"
    },
    {
        "id": 44,
        "STR": "20",
        "STR_GAIN": "2.2",
        "STR_30": "83.8",
        "AGI": "34",
        "AGI_GAIN": "2.8",
        "AGI_30": "115.2",
        "INT": "14",
        "INT_GAIN": "1.4",
        "INT_30": "54.6",
        "TOTAL": "68",
        "TOTAL_GAIN": "6.4",
        "TOTAL_30": "253.6",
        "MS": "305",
        "ARMOR": "5.67",
        "DMG_MIN": "50",
        "DMG_MAX": "54",
        "RANGE": "150",
        "ATTACKSPEED": "110",
        "BAT": "1.4",
        "ATK_PT": "0.33",
        "ATK_BS": "0.84",
        "VIS_DAY": "1800",
        "VIS_NIGHT": "800",
        "TURNRATE": "0.6",
        "COLLISION": "24",
        "HP_SEC": "2.5",
        "LEGS": "2"
    },
    {
        "id": 45,
        "STR": "18",
        "STR_GAIN": "2.3",
        "STR_30": "84.7",
        "AGI": "15",
        "AGI_GAIN": "1.6",
        "AGI_30": "61.4",
        "INT": "23",
        "INT_GAIN": "3.2",
        "INT_30": "115.8",
        "TOTAL": "56",
        "TOTAL_GAIN": "7.1",
        "TOTAL_30": "261.9",
        "MS": "330",
        "ARMOR": "2.5",
        "DMG_MIN": "41",
        "DMG_MAX": "48",
        "RANGE": "600",
        "ATTACKSPEED": "100",
        "BAT": "1.7",
        "ATK_PT": "0.3",
        "ATK_BS": "0.85",
        "VIS_DAY": "1800",
        "VIS_NIGHT": "800",
        "TURNRATE": "0.6",
        "COLLISION": "24",
        "HP_SEC": "2.05",
        "LEGS": "2"
    },
    {
        "id": 46,
        "STR": "24",
        "STR_GAIN": "3.8",
        "STR_30": "134.2",
        "AGI": "14",
        "AGI_GAIN": "1.6",
        "AGI_30": "60.4",
        "INT": "18",
        "INT_GAIN": "1.8",
        "INT_30": "70.2",
        "TOTAL": "56",
        "TOTAL_GAIN": "7.2",
        "TOTAL_30": "264.8",
        "MS": "315",
        "ARMOR": "4.33",
        "DMG_MIN": "50",
        "DMG_MAX": "60",
        "RANGE": "150",
        "ATTACKSPEED": "100",
        "BAT": "1.7",
        "ATK_PT": "0.4",
        "ATK_BS": "0.3",
        "VIS_DAY": "1800",
        "VIS_NIGHT": "800",
        "TURNRATE": "0.6",
        "COLLISION": "24",
        "HP_SEC": "3.15",
        "LEGS": "2"
    },
    {
        "id": 47,
        "STR": "25",
        "STR_GAIN": "3.3",
        "STR_30": "120.7",
        "AGI": "18",
        "AGI_GAIN": "1.7",
        "AGI_30": "67.3",
        "INT": "20",
        "INT_GAIN": "2.2",
        "INT_30": "83.8",
        "TOTAL": "63",
        "TOTAL_GAIN": "7.2",
        "TOTAL_30": "271.8",
        "MS": "330",
        "ARMOR": "3",
        "DMG_MIN": "60",
        "DMG_MAX": "64",
        "RANGE": "150",
        "ATTACKSPEED": "100",
        "BAT": "1.7",
        "ATK_PT": "0.46",
        "ATK_BS": "0.64",
        "VIS_DAY": "1800",
        "VIS_NIGHT": "800",
        "TURNRATE": "0.6",
        "COLLISION": "24",
        "HP_SEC": "2.75",
        "LEGS": "2"
    },
    {
        "id": 48,
        "STR": "20",
        "STR_GAIN": "2.5",
        "STR_30": "92.5",
        "AGI": "23",
        "AGI_GAIN": "2.8",
        "AGI_30": "104.2",
        "INT": "22",
        "INT_GAIN": "3.5",
        "INT_30": "123.5",
        "TOTAL": "65",
        "TOTAL_GAIN": "8.8",
        "TOTAL_30": "320.2",
        "MS": "325",
        "ARMOR": "3.83",
        "DMG_MIN": "47",
        "DMG_MAX": "51",
        "RANGE": "575",
        "ATTACKSPEED": "100",
        "BAT": "1.7",
        "ATK_PT": "0.4",
        "ATK_BS": "0.6",
        "VIS_DAY": "1800",
        "VIS_NIGHT": "800",
        "TURNRATE": "0.6",
        "COLLISION": "24",
        "HP_SEC": "2.25",
        "LEGS": "4"
    },
    {
        "id": 49,
        "STR": "20",
        "STR_GAIN": "2.1",
        "STR_30": "80.9",
        "AGI": "17",
        "AGI_GAIN": "2.0",
        "AGI_30": "75",
        "INT": "24",
        "INT_GAIN": "3.6",
        "INT_30": "128.4",
        "TOTAL": "61",
        "TOTAL_GAIN": "7.7",
        "TOTAL_30": "284.3",
        "MS": "295",
        "ARMOR": "1.83",
        "DMG_MIN": "48",
        "DMG_MAX": "57",
        "RANGE": "550",
        "ATTACKSPEED": "100",
        "BAT": "1.7",
        "ATK_PT": "0.46",
        "ATK_BS": "0.54",
        "VIS_DAY": "1800",
        "VIS_NIGHT": "800",
        "TURNRATE": "0.7",
        "COLLISION": "24",
        "HP_SEC": "2.25",
        "LEGS": "2"
    },
    {
        "id": 50,
        "STR": "25",
        "STR_GAIN": "2.4",
        "STR_30": "94.6",
        "AGI": "19",
        "AGI_GAIN": "2.6",
        "AGI_30": "94.4",
        "INT": "15",
        "INT_GAIN": "1.8",
        "INT_30": "67.2",
        "TOTAL": "59",
        "TOTAL_GAIN": "6.8",
        "TOTAL_30": "256.2",
        "MS": "320",
        "ARMOR": "4.17",
        "DMG_MIN": "47",
        "DMG_MAX": "53",
        "RANGE": "150",
        "ATTACKSPEED": "120",
        "BAT": "1.7",
        "ATK_PT": "0.39",
        "ATK_BS": "0.44",
        "VIS_DAY": "1800",
        "VIS_NIGHT": "800",
        "TURNRATE": "0.9",
        "COLLISION": "24",
        "HP_SEC": "2.75",
        "LEGS": "2"
    },
    {
        "id": 51,
        "STR": "20",
        "STR_GAIN": "2.4",
        "STR_30": "89.6",
        "AGI": "23",
        "AGI_GAIN": "2.4",
        "AGI_30": "92.6",
        "INT": "30",
        "INT_GAIN": "3.8",
        "INT_30": "140.2",
        "TOTAL": "73",
        "TOTAL_GAIN": "8.6",
        "TOTAL_30": "322.4",
        "MS": "290",
        "ARMOR": "3.83",
        "DMG_MIN": "51",
        "DMG_MAX": "59",
        "RANGE": "670",
        "ATTACKSPEED": "100",
        "BAT": "1.6",
        "ATK_PT": "0.65",
        "ATK_BS": "0.6",
        "VIS_DAY": "1800",
        "VIS_NIGHT": "800",
        "TURNRATE": "0.6",
        "COLLISION": "24",
        "HP_SEC": "2.25",
        "LEGS": "2"
    },
    {
        "id": 52,
        "STR": "18",
        "STR_GAIN": "2.2",
        "STR_30": "81.8",
        "AGI": "18",
        "AGI_GAIN": "1.5",
        "AGI_30": "61.5",
        "INT": "18",
        "INT_GAIN": "3.5",
        "INT_30": "119.5",
        "TOTAL": "54",
        "TOTAL_GAIN": "7.2",
        "TOTAL_30": "262.8",
        "MS": "290",
        "ARMOR": "2",
        "DMG_MIN": "47",
        "DMG_MAX": "53",
        "RANGE": "600",
        "ATTACKSPEED": "115",
        "BAT": "1.7",
        "ATK_PT": "0.43",
        "ATK_BS": "0.74",
        "VIS_DAY": "1800",
        "VIS_NIGHT": "800",
        "TURNRATE": "0.6",
        "COLLISION": "24",
        "HP_SEC": "2.05",
        "LEGS": "2"
    },
    {
        "id": 53,
        "STR": "18",
        "STR_GAIN": "2.5",
        "STR_30": "90.5",
        "AGI": "20",
        "AGI_GAIN": "2.8",
        "AGI_30": "101.2",
        "INT": "13",
        "INT_GAIN": "1.4",
        "INT_30": "53.6",
        "TOTAL": "51",
        "TOTAL_GAIN": "6.7",
        "TOTAL_30": "245.3",
        "MS": "325",
        "ARMOR": "1.33",
        "DMG_MIN": "38",
        "DMG_MAX": "42",
        "RANGE": "550",
        "ATTACKSPEED": "100",
        "BAT": "1.6",
        "ATK_PT": "0.33",
        "ATK_BS": "0.53",
        "VIS_DAY": "1800",
        "VIS_NIGHT": "800",
        "TURNRATE": "0.6",
        "COLLISION": "24",
        "HP_SEC": "2.05",
        "LEGS": "2"
    },
    {
        "id": 54,
        "STR": "21",
        "STR_GAIN": "2.2",
        "STR_30": "84.8",
        "AGI": "24",
        "AGI_GAIN": "3.4",
        "AGI_30": "122.6",
        "INT": "23",
        "INT_GAIN": "1.9",
        "INT_30": "78.1",
        "TOTAL": "68",
        "TOTAL_GAIN": "7.5",
        "TOTAL_30": "285.5",
        "MS": "325",
        "ARMOR": "6",
        "DMG_MIN": "50",
        "DMG_MAX": "56",
        "RANGE": "330",
        "ATTACKSPEED": "100",
        "BAT": "1.7",
        "ATK_PT": "0.35",
        "ATK_BS": "0.54",
        "VIS_DAY": "1800",
        "VIS_NIGHT": "800",
        "TURNRATE": "0.6",
        "COLLISION": "24",
        "HP_SEC": "2.6",
        "LEGS": "2"
    },
    {
        "id": 55,
        "STR": "26",
        "STR_GAIN": "3.4",
        "STR_30": "124.6",
        "AGI": "16",
        "AGI_GAIN": "1.7",
        "AGI_30": "65.3",
        "INT": "23",
        "INT_GAIN": "1.7",
        "INT_30": "72.3",
        "TOTAL": "65",
        "TOTAL_GAIN": "6.8",
        "TOTAL_30": "262.2",
        "MS": "315",
        "ARMOR": "2.67",
        "DMG_MIN": "50",
        "DMG_MAX": "55",
        "RANGE": "150",
        "ATTACKSPEED": "100",
        "BAT": "1.7",
        "ATK_PT": "0.55",
        "ATK_BS": "0.25",
        "VIS_DAY": "1800",
        "VIS_NIGHT": "800",
        "TURNRATE": "0.6",
        "COLLISION": "8",
        "HP_SEC": "2.85",
        "LEGS": "2"
    },
    {
        "id": 56,
        "STR": "25",
        "STR_GAIN": "3.5",
        "STR_30": "126.5",
        "AGI": "15",
        "AGI_GAIN": "2.5",
        "AGI_30": "87.5",
        "INT": "19",
        "INT_GAIN": "2.1",
        "INT_30": "79.9",
        "TOTAL": "59",
        "TOTAL_GAIN": "8.1",
        "TOTAL_30": "293.9",
        "MS": "305",
        "ARMOR": "3.5",
        "DMG_MIN": "57",
        "DMG_MAX": "65",
        "RANGE": "150",
        "ATTACKSPEED": "100",
        "BAT": "1.8",
        "ATK_PT": "0.5",
        "ATK_BS": "0.84",
        "VIS_DAY": "1800",
        "VIS_NIGHT": "800",
        "TURNRATE": "0.8",
        "COLLISION": "24",
        "HP_SEC": "3",
        "LEGS": "4"
    },
    {
        "id": 57,
        "STR": "23",
        "STR_GAIN": "3.3",
        "STR_30": "118.7",
        "AGI": "20",
        "AGI_GAIN": "2.4",
        "AGI_30": "89.6",
        "INT": "19",
        "INT_GAIN": "1.9",
        "INT_30": "74.1",
        "TOTAL": "62",
        "TOTAL_GAIN": "7.6",
        "TOTAL_30": "282.4",
        "MS": "310",
        "ARMOR": "3.33",
        "DMG_MIN": "56",
        "DMG_MAX": "60",
        "RANGE": "150",
        "ATTACKSPEED": "100",
        "BAT": "1.7",
        "ATK_PT": "0.3",
        "ATK_BS": "0.5",
        "VIS_DAY": "1800",
        "VIS_NIGHT": "800",
        "TURNRATE": "0.9",
        "COLLISION": "24",
        "HP_SEC": "2.55",
        "LEGS": "2"
    },
    {
        "id": 58,
        "STR": "23",
        "STR_GAIN": "3.7",
        "STR_30": "130.3",
        "AGI": "20",
        "AGI_GAIN": "1.7",
        "AGI_30": "69.3",
        "INT": "21",
        "INT_GAIN": "2.2",
        "INT_30": "84.8",
        "TOTAL": "64",
        "TOTAL_GAIN": "7.6",
        "TOTAL_30": "284.4",
        "MS": "310",
        "ARMOR": "2.33",
        "DMG_MIN": "52",
        "DMG_MAX": "60",
        "RANGE": "250",
        "ATTACKSPEED": "100",
        "BAT": "1.8",
        "ATK_PT": "0.4",
        "ATK_BS": "1.38",
        "VIS_DAY": "1800",
        "VIS_NIGHT": "800",
        "TURNRATE": "0.8",
        "COLLISION": "24",
        "HP_SEC": "2.55",
        "LEGS": "2"
    },
    {
        "id": 59,
        "STR": "17",
        "STR_GAIN": "1.5",
        "STR_30": "60.5",
        "AGI": "22",
        "AGI_GAIN": "3.4",
        "AGI_30": "120.6",
        "INT": "23",
        "INT_GAIN": "3.4",
        "INT_30": "121.6",
        "TOTAL": "62",
        "TOTAL_GAIN": "8.3",
        "TOTAL_30": "302.7",
        "MS": "275",
        "ARMOR": "2.67",
        "DMG_MIN": "48",
        "DMG_MAX": "54",
        "RANGE": "600",
        "ATTACKSPEED": "100",
        "BAT": "1.7",
        "ATK_PT": "0.5",
        "ATK_BS": "0.6",
        "VIS_DAY": "1800",
        "VIS_NIGHT": "800",
        "TURNRATE": "0.6",
        "COLLISION": "24",
        "HP_SEC": "1.95",
        "LEGS": "0"
    },
    {
        "id": 60,
        "STR": "24",
        "STR_GAIN": "2.2",
        "STR_30": "87.8",
        "AGI": "17",
        "AGI_GAIN": "2.2",
        "AGI_30": "80.8",
        "INT": "20",
        "INT_GAIN": "1.9",
        "INT_30": "75.1",
        "TOTAL": "61",
        "TOTAL_GAIN": "6.3",
        "TOTAL_30": "243.7",
        "MS": "330",
        "ARMOR": "6.83",
        "DMG_MIN": "46",
        "DMG_MAX": "52",
        "RANGE": "150",
        "ATTACKSPEED": "100",
        "BAT": "1.7",
        "ATK_PT": "0.38",
        "ATK_BS": "0.6",
        "VIS_DAY": "1800",
        "VIS_NIGHT": "800",
        "TURNRATE": "0.7",
        "COLLISION": "8",
        "HP_SEC": "2.65",
        "LEGS": "2"
    },
    {
        "id": 61,
        "STR": "18",
        "STR_GAIN": "2.2",
        "STR_30": "81.8",
        "AGI": "24",
        "AGI_GAIN": "3.4",
        "AGI_30": "122.6",
        "INT": "22",
        "INT_GAIN": "1.9",
        "INT_30": "77.1",
        "TOTAL": "64",
        "TOTAL_GAIN": "7.5",
        "TOTAL_30": "281.5",
        "MS": "290",
        "ARMOR": "2",
        "DMG_MIN": "48",
        "DMG_MAX": "54",
        "RANGE": "630",
        "ATTACKSPEED": "110",
        "BAT": "1.7",
        "ATK_PT": "0.35",
        "ATK_BS": "0.7",
        "VIS_DAY": "1800",
        "VIS_NIGHT": "800",
        "TURNRATE": "0.6",
        "COLLISION": "24",
        "HP_SEC": "2.05",
        "LEGS": "2"
    },
    {
        "id": 62,
        "STR": "18",
        "STR_GAIN": "2.8",
        "STR_30": "99.2",
        "AGI": "22",
        "AGI_GAIN": "3.7",
        "AGI_30": "129.3",
        "INT": "20",
        "INT_GAIN": "1.8",
        "INT_30": "72.2",
        "TOTAL": "60",
        "TOTAL_GAIN": "8.3",
        "TOTAL_30": "300.7",
        "MS": "300",
        "ARMOR": "5.67",
        "DMG_MIN": "51",
        "DMG_MAX": "55",
        "RANGE": "300",
        "ATTACKSPEED": "100",
        "BAT": "1.7",
        "ATK_PT": "0.45",
        "ATK_BS": "0.2",
        "VIS_DAY": "1800",
        "VIS_NIGHT": "800",
        "TURNRATE": "0.6",
        "COLLISION": "8",
        "HP_SEC": "2.8",
        "LEGS": "2"
    },
    {
        "id": 63,
        "STR": "22",
        "STR_GAIN": "3.0",
        "STR_30": "109",
        "AGI": "24",
        "AGI_GAIN": "3.9",
        "AGI_30": "137.1",
        "INT": "19",
        "INT_GAIN": "1.8",
        "INT_30": "71.2",
        "TOTAL": "65",
        "TOTAL_GAIN": "8.7",
        "TOTAL_30": "317.3",
        "MS": "285",
        "ARMOR": "2",
        "DMG_MIN": "33",
        "DMG_MAX": "42",
        "RANGE": "350",
        "ATTACKSPEED": "100",
        "BAT": "1.5",
        "ATK_PT": "0.5",
        "ATK_BS": "0.5",
        "VIS_DAY": "1800",
        "VIS_NIGHT": "800",
        "TURNRATE": "0.7",
        "COLLISION": "24",
        "HP_SEC": "2.45",
        "LEGS": "0"
    },
    {
        "id": 64,
        "STR": "21",
        "STR_GAIN": "2.8",
        "STR_30": "102.2",
        "AGI": "21",
        "AGI_GAIN": "3.3",
        "AGI_30": "116.7",
        "INT": "21",
        "INT_GAIN": "2.0",
        "INT_30": "79",
        "TOTAL": "63",
        "TOTAL_GAIN": "8.1",
        "TOTAL_30": "297.9",
        "MS": "330",
        "ARMOR": "6.5",
        "DMG_MIN": "44",
        "DMG_MAX": "46",
        "RANGE": "150",
        "ATTACKSPEED": "100",
        "BAT": "1.7",
        "ATK_PT": "0.5",
        "ATK_BS": "0.5",
        "VIS_DAY": "1800",
        "VIS_NIGHT": "800",
        "TURNRATE": "0.6",
        "COLLISION": "8",
        "HP_SEC": "3.6",
        "LEGS": "0"
    },
    {
        "id": 65,
        "STR": "21",
        "STR_GAIN": "2.6",
        "STR_30": "96.4",
        "AGI": "22",
        "AGI_GAIN": "3.6",
        "AGI_30": "126.4",
        "INT": "23",
        "INT_GAIN": "3.7",
        "INT_30": "130.3",
        "TOTAL": "66",
        "TOTAL_GAIN": "9.9",
        "TOTAL_30": "353.1",
        "MS": "295",
        "ARMOR": "3.67",
        "DMG_MIN": "50",
        "DMG_MAX": "60",
        "RANGE": "600",
        "ATTACKSPEED": "100",
        "BAT": "1.7",
        "ATK_PT": "0.4",
        "ATK_BS": "0.6",
        "VIS_DAY": "1800",
        "VIS_NIGHT": "800",
        "TURNRATE": "0.9",
        "COLLISION": "24",
        "HP_SEC": "2.35",
        "LEGS": "2"
    },
    {
        "id": 66,
        "STR": "18",
        "STR_GAIN": "2.3",
        "STR_30": "84.7",
        "AGI": "12",
        "AGI_GAIN": "1.3",
        "AGI_30": "49.7",
        "INT": "21",
        "INT_GAIN": "2.7",
        "INT_30": "99.3",
        "TOTAL": "51",
        "TOTAL_GAIN": "6.3",
        "TOTAL_30": "233.7",
        "MS": "280",
        "ARMOR": "3",
        "DMG_MIN": "47",
        "DMG_MAX": "51",
        "RANGE": "500",
        "ATTACKSPEED": "100",
        "BAT": "1.7",
        "ATK_PT": "0.3",
        "ATK_BS": "0.47",
        "VIS_DAY": "1800",
        "VIS_NIGHT": "800",
        "TURNRATE": "0.6",
        "COLLISION": "24",
        "HP_SEC": "2.05",
        "LEGS": "2"
    },
    {
        "id": 67,
        "STR": "23",
        "STR_GAIN": "3.0",
        "STR_30": "110",
        "AGI": "18",
        "AGI_GAIN": "2.2",
        "AGI_30": "81.8",
        "INT": "15",
        "INT_GAIN": "1.6",
        "INT_30": "61.4",
        "TOTAL": "56",
        "TOTAL_GAIN": "6.8",
        "TOTAL_30": "253.2",
        "MS": "295",
        "ARMOR": "5",
        "DMG_MIN": "63",
        "DMG_MAX": "67",
        "RANGE": "150",
        "ATTACKSPEED": "100",
        "BAT": "1.7",
        "ATK_PT": "0.55",
        "ATK_BS": "0.55",
        "VIS_DAY": "800",
        "VIS_NIGHT": "1800",
        "TURNRATE": "0.6",
        "COLLISION": "24",
        "HP_SEC": "4.3",
        "LEGS": "2"
    },
    {
        "id": 68,
        "STR": "17",
        "STR_GAIN": "2.5",
        "STR_30": "89.5",
        "AGI": "18",
        "AGI_GAIN": "2.5",
        "AGI_30": "90.5",
        "INT": "21",
        "INT_GAIN": "2.1",
        "INT_30": "81.9",
        "TOTAL": "56",
        "TOTAL_GAIN": "7.1",
        "TOTAL_30": "261.9",
        "MS": "310",
        "ARMOR": "4",
        "DMG_MIN": "45",
        "DMG_MAX": "49",
        "RANGE": "150",
        "ATTACKSPEED": "100",
        "BAT": "1.7",
        "ATK_PT": "0.46",
        "ATK_BS": "0.54",
        "VIS_DAY": "1800",
        "VIS_NIGHT": "800",
        "TURNRATE": "0.6",
        "COLLISION": "24",
        "HP_SEC": "3.7",
        "LEGS": "6"
    },
    {
        "id": 69,
        "STR": "23",
        "STR_GAIN": "3.3",
        "STR_30": "118.7",
        "AGI": "14",
        "AGI_GAIN": "1.5",
        "AGI_30": "57.5",
        "INT": "15",
        "INT_GAIN": "2.5",
        "INT_30": "87.5",
        "TOTAL": "52",
        "TOTAL_GAIN": "7.3",
        "TOTAL_30": "263.7",
        "MS": "290",
        "ARMOR": "7.33",
        "DMG_MIN": "49",
        "DMG_MAX": "55",
        "RANGE": "150",
        "ATTACKSPEED": "100",
        "BAT": "1.7",
        "ATK_PT": "0.3",
        "ATK_BS": "0.3",
        "VIS_DAY": "1800",
        "VIS_NIGHT": "800",
        "TURNRATE": "0.6",
        "COLLISION": "24",
        "HP_SEC": "5.55",
        "LEGS": "2"
    },
    {
        "id": 70,
        "STR": "23",
        "STR_GAIN": "3.1",
        "STR_30": "112.9",
        "AGI": "15",
        "AGI_GAIN": "2.0",
        "AGI_30": "73",
        "INT": "16",
        "INT_GAIN": "2.1",
        "INT_30": "76.9",
        "TOTAL": "54",
        "TOTAL_GAIN": "7.2",
        "TOTAL_30": "262.8",
        "MS": "315",
        "ARMOR": "4.5",
        "DMG_MIN": "54",
        "DMG_MAX": "64",
        "RANGE": "150",
        "ATTACKSPEED": "100",
        "BAT": "1.7",
        "ATK_PT": "0.433",
        "ATK_BS": "0.567",
        "VIS_DAY": "1800",
        "VIS_NIGHT": "800",
        "TURNRATE": "0.6",
        "COLLISION": "24",
        "HP_SEC": "2.55",
        "LEGS": "2"
    },
    {
        "id": 71,
        "STR": "20",
        "STR_GAIN": "2.4",
        "STR_30": "89.6",
        "AGI": "15",
        "AGI_GAIN": "1.7",
        "AGI_30": "64.3",
        "INT": "26",
        "INT_GAIN": "3.8",
        "INT_30": "136.2",
        "TOTAL": "61",
        "TOTAL_GAIN": "7.9",
        "TOTAL_30": "290.1",
        "MS": "295",
        "ARMOR": "3.5",
        "DMG_MIN": "39",
        "DMG_MAX": "45",
        "RANGE": "620",
        "ATTACKSPEED": "100",
        "BAT": "1.7",
        "ATK_PT": "0.3",
        "ATK_BS": "0.7",
        "VIS_DAY": "1800",
        "VIS_NIGHT": "800",
        "TURNRATE": "0.7",
        "COLLISION": "24",
        "HP_SEC": "2.25",
        "LEGS": "0"
    },
    {
        "id": 72,
        "STR": "21",
        "STR_GAIN": "2.9",
        "STR_30": "105.1",
        "AGI": "22",
        "AGI_GAIN": "1.6",
        "AGI_30": "68.4",
        "INT": "30",
        "INT_GAIN": "4.2",
        "INT_30": "151.8",
        "TOTAL": "73",
        "TOTAL_GAIN": "8.7",
        "TOTAL_30": "325.3",
        "MS": "320",
        "ARMOR": "6.17",
        "DMG_MIN": "49",
        "DMG_MAX": "61",
        "RANGE": "450",
        "ATTACKSPEED": "100",
        "BAT": "1.9",
        "ATK_PT": "0.46",
        "ATK_BS": "0.54",
        "VIS_DAY": "1800",
        "VIS_NIGHT": "800",
        "TURNRATE": "0.6",
        "COLLISION": "24",
        "HP_SEC": "3.1",
        "LEGS": "4"
    },
    {
        "id": 73,
        "STR": "17",
        "STR_GAIN": "2.5",
        "STR_30": "89.5",
        "AGI": "18",
        "AGI_GAIN": "3.2",
        "AGI_30": "110.8",
        "INT": "16",
        "INT_GAIN": "1.9",
        "INT_30": "71.1",
        "TOTAL": "51",
        "TOTAL_GAIN": "7.6",
        "TOTAL_30": "271.4",
        "MS": "300",
        "ARMOR": "4",
        "DMG_MIN": "51",
        "DMG_MAX": "57",
        "RANGE": "150",
        "ATTACKSPEED": "100",
        "BAT": "1.7",
        "ATK_PT": "0.33",
        "ATK_BS": "0.77",
        "VIS_DAY": "1800",
        "VIS_NIGHT": "800",
        "TURNRATE": "0.9",
        "COLLISION": "24",
        "HP_SEC": "1.95",
        "LEGS": "2"
    },
    {
        "id": 74,
        "STR": "21",
        "STR_GAIN": "2.2",
        "STR_30": "84.8",
        "AGI": "23",
        "AGI_GAIN": "3.4",
        "AGI_30": "121.6",
        "INT": "15",
        "INT_GAIN": "1.4",
        "INT_30": "55.6",
        "TOTAL": "59",
        "TOTAL_GAIN": "7.0",
        "TOTAL_30": "262",
        "MS": "305",
        "ARMOR": "4.83",
        "DMG_MIN": "55",
        "DMG_MAX": "57",
        "RANGE": "150",
        "ATTACKSPEED": "100",
        "BAT": "1.7",
        "ATK_PT": "0.3",
        "ATK_BS": "0.7",
        "VIS_DAY": "1800",
        "VIS_NIGHT": "800",
        "TURNRATE": "0.6",
        "COLLISION": "24",
        "HP_SEC": "2.85",
        "LEGS": "2"
    },
    {
        "id": 75,
        "STR": "19",
        "STR_GAIN": "2.2",
        "STR_30": "82.8",
        "AGI": "26",
        "AGI_GAIN": "3.2",
        "AGI_30": "118.8",
        "INT": "21",
        "INT_GAIN": "2.0",
        "INT_30": "79",
        "TOTAL": "66",
        "TOTAL_GAIN": "7.4",
        "TOTAL_30": "280.6",
        "MS": "290",
        "ARMOR": "3.33",
        "DMG_MIN": "52",
        "DMG_MAX": "62",
        "RANGE": "150",
        "ATTACKSPEED": "100",
        "BAT": "1.7",
        "ATK_PT": "0.5",
        "ATK_BS": "0.5",
        "VIS_DAY": "1800",
        "VIS_NIGHT": "800",
        "TURNRATE": "0.6",
        "COLLISION": "8",
        "HP_SEC": "3.4",
        "LEGS": "2"
    },
    {
        "id": 76,
        "STR": "23",
        "STR_GAIN": "3.6",
        "STR_30": "127.4",
        "AGI": "12",
        "AGI_GAIN": "1.5",
        "AGI_30": "55.5",
        "INT": "16",
        "INT_GAIN": "1.8",
        "INT_30": "68.2",
        "TOTAL": "51",
        "TOTAL_GAIN": "6.9",
        "TOTAL_30": "251.1",
        "MS": "280",
        "ARMOR": "1",
        "DMG_MIN": "49",
        "DMG_MAX": "59",
        "RANGE": "525",
        "ATTACKSPEED": "100",
        "BAT": "1.7",
        "ATK_PT": "0.35",
        "ATK_BS": "0.633",
        "VIS_DAY": "1800",
        "VIS_NIGHT": "800",
        "TURNRATE": "0.9",
        "COLLISION": "24",
        "HP_SEC": "3.3",
        "LEGS": "2"
    },
    {
        "id": 77,
        "STR": "26",
        "STR_GAIN": "4.3",
        "STR_30": "150.7",
        "AGI": "15",
        "AGI_GAIN": "1.0",
        "AGI_30": "44",
        "INT": "16",
        "INT_GAIN": "1.4",
        "INT_30": "56.6",
        "TOTAL": "57",
        "TOTAL_GAIN": "6.7",
        "TOTAL_30": "251.3",
        "MS": "305",
        "ARMOR": "4.5",
        "DMG_MIN": "62",
        "DMG_MAX": "64",
        "RANGE": "150",
        "ATTACKSPEED": "100",
        "BAT": "1.8",
        "ATK_PT": "0.6",
        "ATK_BS": "0",
        "VIS_DAY": "1800",
        "VIS_NIGHT": "800",
        "TURNRATE": "0.6",
        "COLLISION": "24",
        "HP_SEC": "2.6",
        "LEGS": "2"
    },
    {
        "id": 78,
        "STR": "17",
        "STR_GAIN": "2.4",
        "STR_30": "86.6",
        "AGI": "22",
        "AGI_GAIN": "2.5",
        "AGI_30": "94.5",
        "INT": "23",
        "INT_GAIN": "3.5",
        "INT_30": "124.5",
        "TOTAL": "62",
        "TOTAL_GAIN": "8.4",
        "TOTAL_30": "305.6",
        "MS": "290",
        "ARMOR": "0.67",
        "DMG_MIN": "45",
        "DMG_MAX": "53",
        "RANGE": "550",
        "ATTACKSPEED": "100",
        "BAT": "1.7",
        "ATK_PT": "0.5",
        "ATK_BS": "0.9",
        "VIS_DAY": "1800",
        "VIS_NIGHT": "800",
        "TURNRATE": "0.9",
        "COLLISION": "24",
        "HP_SEC": "2.2",
        "LEGS": "2"
    },
    {
        "id": 79,
        "STR": "25",
        "STR_GAIN": "3.0",
        "STR_30": "112",
        "AGI": "14",
        "AGI_GAIN": "1.4",
        "AGI_30": "54.6",
        "INT": "16",
        "INT_GAIN": "1.8",
        "INT_30": "68.2",
        "TOTAL": "55",
        "TOTAL_GAIN": "6.2",
        "TOTAL_30": "234.8",
        "MS": "280",
        "ARMOR": "1.33",
        "DMG_MIN": "67",
        "DMG_MAX": "73",
        "RANGE": "175",
        "ATTACKSPEED": "100",
        "BAT": "1.7",
        "ATK_PT": "0.5",
        "ATK_BS": "1.17",
        "VIS_DAY": "1800",
        "VIS_NIGHT": "800",
        "TURNRATE": "0.7",
        "COLLISION": "24",
        "HP_SEC": "4.5",
        "LEGS": "2"
    },
    {
        "id": 80,
        "STR": "19",
        "STR_GAIN": "2.0",
        "STR_30": "77",
        "AGI": "24",
        "AGI_GAIN": "1.3",
        "AGI_30": "61.7",
        "INT": "24",
        "INT_GAIN": "5.2",
        "INT_30": "174.8",
        "TOTAL": "67",
        "TOTAL_GAIN": "8.5",
        "TOTAL_30": "313.5",
        "MS": "330",
        "ARMOR": "4",
        "DMG_MIN": "45",
        "DMG_MAX": "52",
        "RANGE": "630",
        "ATTACKSPEED": "100",
        "BAT": "1.7",
        "ATK_PT": "0.5",
        "ATK_BS": "0.5",
        "VIS_DAY": "1800",
        "VIS_NIGHT": "800",
        "TURNRATE": "0.6",
        "COLLISION": "24",
        "HP_SEC": "2.15",
        "LEGS": "2"
    },
    {
        "id": 81,
        "STR": "18",
        "STR_GAIN": "2.4",
        "STR_30": "87.6",
        "AGI": "22",
        "AGI_GAIN": "2.5",
        "AGI_30": "94.5",
        "INT": "25",
        "INT_GAIN": "3.4",
        "INT_30": "123.6",
        "TOTAL": "65",
        "TOTAL_GAIN": "8.3",
        "TOTAL_30": "305.7",
        "MS": "290",
        "ARMOR": "3.67",
        "DMG_MIN": "49",
        "DMG_MAX": "55",
        "RANGE": "550",
        "ATTACKSPEED": "100",
        "BAT": "1.5",
        "ATK_PT": "0.56",
        "ATK_BS": "0.41",
        "VIS_DAY": "1800",
        "VIS_NIGHT": "800",
        "TURNRATE": "0.6",
        "COLLISION": "24",
        "HP_SEC": "2.05",
        "LEGS": "2"
    },
    {
        "id": 82,
        "STR": "22",
        "STR_GAIN": "2.8",
        "STR_30": "103.2",
        "AGI": "22",
        "AGI_GAIN": "2.6",
        "AGI_30": "97.4",
        "INT": "21",
        "INT_GAIN": "2.2",
        "INT_30": "84.8",
        "TOTAL": "65",
        "TOTAL_GAIN": "7.6",
        "TOTAL_30": "285.4",
        "MS": "290",
        "ARMOR": "2.67",
        "DMG_MIN": "45",
        "DMG_MAX": "47",
        "RANGE": "475",
        "ATTACKSPEED": "100",
        "BAT": "1.7",
        "ATK_PT": "0.3",
        "ATK_BS": "0.4",
        "VIS_DAY": "1800",
        "VIS_NIGHT": "800",
        "TURNRATE": "0.6",
        "COLLISION": "24",
        "HP_SEC": "3.2",
        "LEGS": "0"
    },
    {
        "id": 83,
        "STR": "18",
        "STR_GAIN": "2.6",
        "STR_30": "93.4",
        "AGI": "18",
        "AGI_GAIN": "1.4",
        "AGI_30": "58.6",
        "INT": "14",
        "INT_GAIN": "1.3",
        "INT_30": "51.7",
        "TOTAL": "50",
        "TOTAL_GAIN": "5.3",
        "TOTAL_30": "203.7",
        "MS": "315",
        "ARMOR": "6",
        "DMG_MIN": "59",
        "DMG_MAX": "63",
        "RANGE": "150",
        "ATTACKSPEED": "100",
        "BAT": "1.7",
        "ATK_PT": "0.3",
        "ATK_BS": "0.3",
        "VIS_DAY": "1800",
        "VIS_NIGHT": "800",
        "TURNRATE": "0.6",
        "COLLISION": "24",
        "HP_SEC": "4.3",
        "LEGS": "2"
    },
    {
        "id": 84,
        "STR": "21",
        "STR_GAIN": "2.0",
        "STR_30": "79",
        "AGI": "23",
        "AGI_GAIN": "2.5",
        "AGI_30": "95.5",
        "INT": "25",
        "INT_GAIN": "3.1",
        "INT_30": "114.9",
        "TOTAL": "69",
        "TOTAL_GAIN": "7.6",
        "TOTAL_30": "289.4",
        "MS": "290",
        "ARMOR": "3.83",
        "DMG_MIN": "49",
        "DMG_MAX": "55",
        "RANGE": "550",
        "ATTACKSPEED": "100",
        "BAT": "1.7",
        "ATK_PT": "0.4",
        "ATK_BS": "0.77",
        "VIS_DAY": "1800",
        "VIS_NIGHT": "800",
        "TURNRATE": "0.7",
        "COLLISION": "24",
        "HP_SEC": "2.35",
        "LEGS": "2"
    },
    {
        "id": 85,
        "STR": "22",
        "STR_GAIN": "2.7",
        "STR_30": "100.3",
        "AGI": "19",
        "AGI_GAIN": "1.8",
        "AGI_30": "71.2",
        "INT": "19",
        "INT_GAIN": "1.8",
        "INT_30": "71.2",
        "TOTAL": "60",
        "TOTAL_GAIN": "6.3",
        "TOTAL_30": "242.7",
        "MS": "290",
        "ARMOR": "3.17",
        "DMG_MIN": "45",
        "DMG_MAX": "55",
        "RANGE": "150",
        "ATTACKSPEED": "110",
        "BAT": "1.7",
        "ATK_PT": "0.53",
        "ATK_BS": "0.47",
        "VIS_DAY": "1800",
        "VIS_NIGHT": "800",
        "TURNRATE": "0.6",
        "COLLISION": "24",
        "HP_SEC": "2.45",
        "LEGS": "6"
    },
    {
        "id": 86,
        "STR": "23",
        "STR_GAIN": "2.6",
        "STR_30": "98.4",
        "AGI": "18",
        "AGI_GAIN": "2.2",
        "AGI_30": "81.8",
        "INT": "22",
        "INT_GAIN": "3.6",
        "INT_30": "126.4",
        "TOTAL": "63",
        "TOTAL_GAIN": "8.4",
        "TOTAL_30": "306.6",
        "MS": "290",
        "ARMOR": "3",
        "DMG_MIN": "51",
        "DMG_MAX": "55",
        "RANGE": "500",
        "ATTACKSPEED": "100",
        "BAT": "1.7",
        "ATK_PT": "0.35",
        "ATK_BS": "0.5",
        "VIS_DAY": "1800",
        "VIS_NIGHT": "800",
        "TURNRATE": "0.6",
        "COLLISION": "24",
        "HP_SEC": "2.55",
        "LEGS": "2"
    },
    {
        "id": 87,
        "STR": "19",
        "STR_GAIN": "2.7",
        "STR_30": "97.3",
        "AGI": "20",
        "AGI_GAIN": "3.5",
        "AGI_30": "121.5",
        "INT": "18",
        "INT_GAIN": "2.2",
        "INT_30": "81.8",
        "TOTAL": "57",
        "TOTAL_GAIN": "8.4",
        "TOTAL_30": "300.6",
        "MS": "305",
        "ARMOR": "4.33",
        "DMG_MIN": "39",
        "DMG_MAX": "45",
        "RANGE": "500",
        "ATTACKSPEED": "100",
        "BAT": "1.6",
        "ATK_PT": "0.5",
        "ATK_BS": "0.54",
        "VIS_DAY": "1800",
        "VIS_NIGHT": "800",
        "TURNRATE": "0.9",
        "COLLISION": "24",
        "HP_SEC": "2.15",
        "LEGS": "0"
    },
    {
        "id": 88,
        "STR": "23",
        "STR_GAIN": "2.3",
        "STR_30": "89.7",
        "AGI": "16",
        "AGI_GAIN": "1.6",
        "AGI_30": "62.4",
        "INT": "25",
        "INT_GAIN": "3.5",
        "INT_30": "126.5",
        "TOTAL": "64",
        "TOTAL_GAIN": "7.4",
        "TOTAL_30": "278.6",
        "MS": "285",
        "ARMOR": "4.67",
        "DMG_MIN": "71",
        "DMG_MAX": "78",
        "RANGE": "400",
        "ATTACKSPEED": "90",
        "BAT": "1.7",
        "ATK_PT": "0.3",
        "ATK_BS": "0.5",
        "VIS_DAY": "1800",
        "VIS_NIGHT": "800",
        "TURNRATE": "0.6",
        "COLLISION": "24",
        "HP_SEC": "3.3",
        "LEGS": "2"
    },
    {
        "id": 89,
        "STR": "19",
        "STR_GAIN": "2.4",
        "STR_30": "88.6",
        "AGI": "22",
        "AGI_GAIN": "2.4",
        "AGI_30": "91.6",
        "INT": "25",
        "INT_GAIN": "2.9",
        "INT_30": "109.1",
        "TOTAL": "66",
        "TOTAL_GAIN": "7.7",
        "TOTAL_30": "289.3",
        "MS": "290",
        "ARMOR": "2.67",
        "DMG_MIN": "43",
        "DMG_MAX": "57",
        "RANGE": "600",
        "ATTACKSPEED": "115",
        "BAT": "1.7",
        "ATK_PT": "0.5",
        "ATK_BS": "0.5",
        "VIS_DAY": "1800",
        "VIS_NIGHT": "800",
        "TURNRATE": "0.6",
        "COLLISION": "24",
        "HP_SEC": "2.15",
        "LEGS": "2"
    },
    {
        "id": 90,
        "STR": "21",
        "STR_GAIN": "2.0",
        "STR_30": "79",
        "AGI": "13",
        "AGI_GAIN": "0.8",
        "AGI_30": "36.2",
        "INT": "25",
        "INT_GAIN": "4.1",
        "INT_30": "143.9",
        "TOTAL": "59",
        "TOTAL_GAIN": "6.9",
        "TOTAL_30": "259.1",
        "MS": "325",
        "ARMOR": "0.17",
        "DMG_MIN": "41",
        "DMG_MAX": "51",
        "RANGE": "625",
        "ATTACKSPEED": "100",
        "BAT": "1.7",
        "ATK_PT": "0.4",
        "ATK_BS": "0.78",
        "VIS_DAY": "1800",
        "VIS_NIGHT": "800",
        "TURNRATE": "0.6",
        "COLLISION": "24",
        "HP_SEC": "2.35",
        "LEGS": "2"
    },
    {
        "id": 91,
        "STR": "21",
        "STR_GAIN": "3.6",
        "STR_30": "125.4",
        "AGI": "17",
        "AGI_GAIN": "2.4",
        "AGI_30": "86.6",
        "INT": "15",
        "INT_GAIN": "1.5",
        "INT_30": "58.5",
        "TOTAL": "53",
        "TOTAL_GAIN": "7.5",
        "TOTAL_30": "270.5",
        "MS": "300",
        "ARMOR": "5.83",
        "DMG_MIN": "51",
        "DMG_MAX": "59",
        "RANGE": "150",
        "ATTACKSPEED": "100",
        "BAT": "1.7",
        "ATK_PT": "0.36",
        "ATK_BS": "0.64",
        "VIS_DAY": "1800",
        "VIS_NIGHT": "800",
        "TURNRATE": "0.6",
        "COLLISION": "24",
        "HP_SEC": "2.6",
        "LEGS": "0"
    },
    {
        "id": 92,
        "STR": "20",
        "STR_GAIN": "1.9",
        "STR_30": "75.1",
        "AGI": "21",
        "AGI_GAIN": "1.7",
        "AGI_30": "70.3",
        "INT": "16",
        "INT_GAIN": "1.7",
        "INT_30": "65.3",
        "TOTAL": "57",
        "TOTAL_GAIN": "5.3",
        "TOTAL_30": "210.7",
        "MS": "300",
        "ARMOR": "3.5",
        "DMG_MIN": "53",
        "DMG_MAX": "61",
        "RANGE": "150",
        "ATTACKSPEED": "110",
        "BAT": "1.7",
        "ATK_PT": "0.5",
        "ATK_BS": "0.3",
        "VIS_DAY": "1800",
        "VIS_NIGHT": "1800",
        "TURNRATE": "0.7",
        "COLLISION": "24",
        "HP_SEC": "3.75",
        "LEGS": "2"
    },
    {
        "id": 93,
        "STR": "20",
        "STR_GAIN": "3.5",
        "STR_30": "121.5",
        "AGI": "16",
        "AGI_GAIN": "1.9",
        "AGI_30": "71.1",
        "INT": "21",
        "INT_GAIN": "2.2",
        "INT_30": "84.8",
        "TOTAL": "57",
        "TOTAL_GAIN": "7.6",
        "TOTAL_30": "277.4",
        "MS": "300",
        "ARMOR": "3.67",
        "DMG_MIN": "46",
        "DMG_MAX": "52",
        "RANGE": "500",
        "ATTACKSPEED": "100",
        "BAT": "1.6",
        "ATK_PT": "0.35",
        "ATK_BS": "1.23",
        "VIS_DAY": "1800",
        "VIS_NIGHT": "800",
        "TURNRATE": "0.6",
        "COLLISION": "24",
        "HP_SEC": "2.75",
        "LEGS": "2"
    },
    {
        "id": 94,
        "STR": "19",
        "STR_GAIN": "2.0",
        "STR_30": "77",
        "AGI": "27",
        "AGI_GAIN": "3.2",
        "AGI_30": "119.8",
        "INT": "15",
        "INT_GAIN": "2.6",
        "INT_30": "90.4",
        "TOTAL": "61",
        "TOTAL_GAIN": "7.8",
        "TOTAL_30": "287.2",
        "MS": "285",
        "ARMOR": "3.5",
        "DMG_MIN": "40",
        "DMG_MAX": "46",
        "RANGE": "550",
        "ATTACKSPEED": "100",
        "BAT": "1.7",
        "ATK_PT": "0.17",
        "ATK_BS": "0.7",
        "VIS_DAY": "1800",
        "VIS_NIGHT": "1400",
        "TURNRATE": "0.7",
        "COLLISION": "24",
        "HP_SEC": "2.15",
        "LEGS": "2"
    },
    {
        "id": 95,
        "STR": "23",
        "STR_GAIN": "2.5",
        "STR_30": "95.5",
        "AGI": "23",
        "AGI_GAIN": "2.1",
        "AGI_30": "83.9",
        "INT": "16",
        "INT_GAIN": "1.9",
        "INT_30": "71.1",
        "TOTAL": "62",
        "TOTAL_GAIN": "6.5",
        "TOTAL_30": "250.5",
        "MS": "290",
        "ARMOR": "4.83",
        "DMG_MIN": "46",
        "DMG_MAX": "50",
        "RANGE": "150",
        "ATTACKSPEED": "90",
        "BAT": "1.7",
        "ATK_PT": "0.3",
        "ATK_BS": "0.7",
        "VIS_DAY": "1800",
        "VIS_NIGHT": "800",
        "TURNRATE": "0.6",
        "COLLISION": "24",
        "HP_SEC": "3.8",
        "LEGS": "0"
    },
    {
        "id": 96,
        "STR": "28",
        "STR_GAIN": "3.0",
        "STR_30": "115",
        "AGI": "17",
        "AGI_GAIN": "1.7",
        "AGI_30": "66.3",
        "INT": "14",
        "INT_GAIN": "1.8",
        "INT_30": "66.2",
        "TOTAL": "59",
        "TOTAL_GAIN": "6.5",
        "TOTAL_30": "247.5",
        "MS": "295",
        "ARMOR": "4.83",
        "DMG_MIN": "59",
        "DMG_MAX": "69",
        "RANGE": "150",
        "ATTACKSPEED": "100",
        "BAT": "1.9",
        "ATK_PT": "0.6",
        "ATK_BS": "0.3",
        "VIS_DAY": "1800",
        "VIS_NIGHT": "800",
        "TURNRATE": "0.6",
        "COLLISION": "24",
        "HP_SEC": "4.05",
        "LEGS": "2"
    },
    {
        "id": 97,
        "STR": "21",
        "STR_GAIN": "2.0",
        "STR_30": "79",
        "AGI": "22",
        "AGI_GAIN": "1.9",
        "AGI_30": "77.1",
        "INT": "23",
        "INT_GAIN": "3.9",
        "INT_30": "136.1",
        "TOTAL": "66",
        "TOTAL_GAIN": "7.8",
        "TOTAL_30": "292.2",
        "MS": "285",
        "ARMOR": "5.67",
        "DMG_MIN": "47",
        "DMG_MAX": "57",
        "RANGE": "480",
        "ATTACKSPEED": "115",
        "BAT": "1.7",
        "ATK_PT": "0.5",
        "ATK_BS": "0.3",
        "VIS_DAY": "1800",
        "VIS_NIGHT": "800",
        "TURNRATE": "0.8",
        "COLLISION": "24",
        "HP_SEC": "2.35",
        "LEGS": "2"
    },
    {
        "id": 98,
        "STR": "22",
        "STR_GAIN": "3.2",
        "STR_30": "114.8",
        "AGI": "21",
        "AGI_GAIN": "2.2",
        "AGI_30": "84.8",
        "INT": "16",
        "INT_GAIN": "1.3",
        "INT_30": "53.7",
        "TOTAL": "59",
        "TOTAL_GAIN": "6.7",
        "TOTAL_30": "253.3",
        "MS": "325",
        "ARMOR": "3.5",
        "DMG_MIN": "63",
        "DMG_MAX": "65",
        "RANGE": "150",
        "ATTACKSPEED": "100",
        "BAT": "1.9",
        "ATK_PT": "0.4",
        "ATK_BS": "0.3",
        "VIS_DAY": "1800",
        "VIS_NIGHT": "800",
        "TURNRATE": "0.6",
        "COLLISION": "24",
        "HP_SEC": "2.45",
        "LEGS": "2"
    },
    {
        "id": 99,
        "STR": "19",
        "STR_GAIN": "2.5",
        "STR_30": "91.5",
        "AGI": "14",
        "AGI_GAIN": "1.3",
        "AGI_30": "51.7",
        "INT": "25",
        "INT_GAIN": "3.0",
        "INT_30": "112",
        "TOTAL": "58",
        "TOTAL_GAIN": "6.8",
        "TOTAL_30": "255.2",
        "MS": "300",
        "ARMOR": "5.33",
        "DMG_MIN": "46",
        "DMG_MAX": "48",
        "RANGE": "700",
        "ATTACKSPEED": "100",
        "BAT": "1.7",
        "ATK_PT": "0.5",
        "ATK_BS": "0.5",
        "VIS_DAY": "1800",
        "VIS_NIGHT": "800",
        "TURNRATE": "0.6",
        "COLLISION": "24",
        "HP_SEC": "2.15",
        "LEGS": "6"
    },
    {
        "id": 100,
        "STR": "21",
        "STR_GAIN": "2.4",
        "STR_30": "90.6",
        "AGI": "23",
        "AGI_GAIN": "3.2",
        "AGI_30": "115.8",
        "INT": "20",
        "INT_GAIN": "2.0",
        "INT_30": "78",
        "TOTAL": "64",
        "TOTAL_GAIN": "7.6",
        "TOTAL_30": "284.4",
        "MS": "305",
        "ARMOR": "4.83",
        "DMG_MIN": "53",
        "DMG_MAX": "59",
        "RANGE": "160",
        "ATTACKSPEED": "100",
        "BAT": "1.7",
        "ATK_PT": "0.3",
        "ATK_BS": "0.5",
        "VIS_DAY": "1800",
        "VIS_NIGHT": "800",
        "TURNRATE": "0.7",
        "COLLISION": "24",
        "HP_SEC": "2.35",
        "LEGS": "2"
    },
    {
        "id": 101,
        "STR": "16",
        "STR_GAIN": "2.0",
        "STR_30": "74",
        "AGI": "22",
        "AGI_GAIN": "4.0",
        "AGI_30": "138",
        "INT": "19",
        "INT_GAIN": "1.6",
        "INT_30": "65.4",
        "TOTAL": "57",
        "TOTAL_GAIN": "7.6",
        "TOTAL_30": "277.4",
        "MS": "315",
        "ARMOR": "8.67",
        "DMG_MIN": "52",
        "DMG_MAX": "58",
        "RANGE": "150",
        "ATTACKSPEED": "110",
        "BAT": "1.5",
        "ATK_PT": "0.3",
        "ATK_BS": "0.6",
        "VIS_DAY": "1800",
        "VIS_NIGHT": "800",
        "TURNRATE": "0.6",
        "COLLISION": "24",
        "HP_SEC": "2.6",
        "LEGS": "2"
    },
    {
        "id": 102,
        "STR": "27",
        "STR_GAIN": "3.5",
        "STR_30": "128.5",
        "AGI": "15",
        "AGI_GAIN": "1.5",
        "AGI_30": "58.5",
        "INT": "18",
        "INT_GAIN": "1.7",
        "INT_30": "67.3",
        "TOTAL": "60",
        "TOTAL_GAIN": "6.7",
        "TOTAL_30": "254.3",
        "MS": "300",
        "ARMOR": "2.5",
        "DMG_MIN": "52",
        "DMG_MAX": "58",
        "RANGE": "150",
        "ATTACKSPEED": "100",
        "BAT": "1.7",
        "ATK_PT": "0.6",
        "ATK_BS": "0.56",
        "VIS_DAY": "1800",
        "VIS_NIGHT": "800",
        "TURNRATE": "0.6",
        "COLLISION": "24",
        "HP_SEC": "2.95",
        "LEGS": "2"
    },
    {
        "id": 103,
        "STR": "24",
        "STR_GAIN": "3.2",
        "STR_30": "116.8",
        "AGI": "16",
        "AGI_GAIN": "1.6",
        "AGI_30": "62.4",
        "INT": "23",
        "INT_GAIN": "2.7",
        "INT_30": "101.3",
        "TOTAL": "63",
        "TOTAL_GAIN": "7.5",
        "TOTAL_30": "280.5",
        "MS": "290",
        "ARMOR": "2.67",
        "DMG_MIN": "51",
        "DMG_MAX": "55",
        "RANGE": "150",
        "ATTACKSPEED": "100",
        "BAT": "1.7",
        "ATK_PT": "0.36",
        "ATK_BS": "0.64",
        "VIS_DAY": "1800",
        "VIS_NIGHT": "800",
        "TURNRATE": "0.6",
        "COLLISION": "24",
        "HP_SEC": "2.65",
        "LEGS": "2"
    },
    {
        "id": 104,
        "STR": "18",
        "STR_GAIN": "2.5",
        "STR_30": "90.5",
        "AGI": "13",
        "AGI_GAIN": "1.2",
        "AGI_30": "47.8",
        "INT": "30",
        "INT_GAIN": "3.3",
        "INT_30": "125.7",
        "TOTAL": "61",
        "TOTAL_GAIN": "7.0",
        "TOTAL_30": "264",
        "MS": "290",
        "ARMOR": "4.17",
        "DMG_MIN": "52",
        "DMG_MAX": "58",
        "RANGE": "500",
        "ATTACKSPEED": "100",
        "BAT": "1.7",
        "ATK_PT": "0.35",
        "ATK_BS": "0.65",
        "VIS_DAY": "1800",
        "VIS_NIGHT": "800",
        "TURNRATE": "0.6",
        "COLLISION": "24",
        "HP_SEC": "2.05",
        "LEGS": "2"
    },
    {
        "id": 105,
        "STR": "30",
        "STR_GAIN": "4.0",
        "STR_30": "146",
        "AGI": "0",
        "AGI_GAIN": "0.0",
        "AGI_30": "0",
        "INT": "17",
        "INT_GAIN": "2.2",
        "INT_30": "80.8",
        "TOTAL": "47",
        "TOTAL_GAIN": "6.2",
        "TOTAL_30": "226.8",
        "MS": "295",
        "ARMOR": "0",
        "DMG_MIN": "61",
        "DMG_MAX": "67",
        "RANGE": "150",
        "ATTACKSPEED": "90",
        "BAT": "1.7",
        "ATK_PT": "0.4",
        "ATK_BS": "0.7",
        "VIS_DAY": "1800",
        "VIS_NIGHT": "800",
        "TURNRATE": "0.6",
        "COLLISION": "24",
        "HP_SEC": "4.5",
        "LEGS": "2"
    },
    {
        "id": 106,
        "STR": "25",
        "STR_GAIN": "3.4",
        "STR_30": "123.6",
        "AGI": "15",
        "AGI_GAIN": "2.0",
        "AGI_30": "73",
        "INT": "20",
        "INT_GAIN": "1.8",
        "INT_30": "72.2",
        "TOTAL": "60",
        "TOTAL_GAIN": "7.2",
        "TOTAL_30": "268.8",
        "MS": "285",
        "ARMOR": "1.5",
        "DMG_MIN": "87",
        "DMG_MAX": "95",
        "RANGE": "150",
        "ATTACKSPEED": "100",
        "BAT": "1.9",
        "ATK_PT": "0.6",
        "ATK_BS": "0.4",
        "VIS_DAY": "1800",
        "VIS_NIGHT": "800",
        "TURNRATE": "0.6",
        "COLLISION": "24",
        "HP_SEC": "2.75",
        "LEGS": "2"
    },
    {
        "id": 107,
        "STR": "21",
        "STR_GAIN": "2.5",
        "STR_30": "93.5",
        "AGI": "21",
        "AGI_GAIN": "3.3",
        "AGI_30": "116.7",
        "INT": "13",
        "INT_GAIN": "1.0",
        "INT_30": "42",
        "TOTAL": "55",
        "TOTAL_GAIN": "6.8",
        "TOTAL_30": "252.2",
        "MS": "290",
        "ARMOR": "2.5",
        "DMG_MIN": "48",
        "DMG_MAX": "56",
        "RANGE": "500",
        "ATTACKSPEED": "100",
        "BAT": "1.7",
        "ATK_PT": "0.3",
        "ATK_BS": "0.3",
        "VIS_DAY": "1800",
        "VIS_NIGHT": "800",
        "TURNRATE": "0.6",
        "COLLISION": "24",
        "HP_SEC": "2.35",
        "LEGS": "2"
    },
    {
        "id": 108,
        "STR": "23",
        "STR_GAIN": "3.9",
        "STR_30": "136.1",
        "AGI": "23",
        "AGI_GAIN": "2.1",
        "AGI_30": "83.9",
        "INT": "18",
        "INT_GAIN": "1.7",
        "INT_30": "67.3",
        "TOTAL": "64",
        "TOTAL_GAIN": "7.7",
        "TOTAL_30": "287.3",
        "MS": "310",
        "ARMOR": "4.83",
        "DMG_MIN": "50",
        "DMG_MAX": "54",
        "RANGE": "150",
        "ATTACKSPEED": "100",
        "BAT": "1.7",
        "ATK_PT": "0.36",
        "ATK_BS": "0.64",
        "VIS_DAY": "1800",
        "VIS_NIGHT": "800",
        "TURNRATE": "0.7",
        "COLLISION": "24",
        "HP_SEC": "3.05",
        "LEGS": "2"
    },
    {
        "id": 109,
        "STR": "25",
        "STR_GAIN": "3.0",
        "STR_30": "112",
        "AGI": "12",
        "AGI_GAIN": "1.6",
        "AGI_30": "58.4",
        "INT": "17",
        "INT_GAIN": "2.3",
        "INT_30": "83.7",
        "TOTAL": "54",
        "TOTAL_GAIN": "6.9",
        "TOTAL_30": "254.1",
        "MS": "290",
        "ARMOR": "5",
        "DMG_MIN": "62",
        "DMG_MAX": "68",
        "RANGE": "200",
        "ATTACKSPEED": "100",
        "BAT": "1.7",
        "ATK_PT": "0.45",
        "ATK_BS": "0.7",
        "VIS_DAY": "1800",
        "VIS_NIGHT": "800",
        "TURNRATE": "0.6",
        "COLLISION": "24",
        "HP_SEC": "2.75",
        "LEGS": "2"
    },
    {
        "id": 110,
        "STR": "22",
        "STR_GAIN": "2.8",
        "STR_30": "103.2",
        "AGI": "10",
        "AGI_GAIN": "1.2",
        "AGI_30": "44.8",
        "INT": "27",
        "INT_GAIN": "2.8",
        "INT_30": "108.2",
        "TOTAL": "59",
        "TOTAL_GAIN": "6.8",
        "TOTAL_30": "256.2",
        "MS": "300",
        "ARMOR": "2.67",
        "DMG_MIN": "57",
        "DMG_MAX": "65",
        "RANGE": "150",
        "ATTACKSPEED": "100",
        "BAT": "1.7",
        "ATK_PT": "0.3",
        "ATK_BS": "0.3",
        "VIS_DAY": "1800",
        "VIS_NIGHT": "800",
        "TURNRATE": "0.6",
        "COLLISION": "24",
        "HP_SEC": "2.45",
        "LEGS": "2"
    },
    {
        "id": 111,
        "STR": "25",
        "STR_GAIN": "2.6",
        "STR_30": "100.4",
        "AGI": "18",
        "AGI_GAIN": "2.6",
        "AGI_30": "93.4",
        "INT": "16",
        "INT_GAIN": "1.5",
        "INT_30": "59.5",
        "TOTAL": "59",
        "TOTAL_GAIN": "6.7",
        "TOTAL_30": "253.3",
        "MS": "310",
        "ARMOR": "4",
        "DMG_MIN": "42",
        "DMG_MAX": "46",
        "RANGE": "150",
        "ATTACKSPEED": "100",
        "BAT": "1.7",
        "ATK_PT": "0.3",
        "ATK_BS": "0.3",
        "VIS_DAY": "1800",
        "VIS_NIGHT": "800",
        "TURNRATE": "0.6",
        "COLLISION": "24",
        "HP_SEC": "3",
        "LEGS": "2"
    },
    {
        "id": 112,
        "STR": "19",
        "STR_GAIN": "2.6",
        "STR_30": "94.4",
        "AGI": "20",
        "AGI_GAIN": "3.2",
        "AGI_30": "112.8",
        "INT": "19",
        "INT_GAIN": "1.5",
        "INT_30": "62.5",
        "TOTAL": "58",
        "TOTAL_GAIN": "7.3",
        "TOTAL_30": "269.7",
        "MS": "295",
        "ARMOR": "3.33",
        "DMG_MIN": "44",
        "DMG_MAX": "50",
        "RANGE": "400",
        "ATTACKSPEED": "100",
        "BAT": "1.7",
        "ATK_PT": "0.33",
        "ATK_BS": "0.64",
        "VIS_DAY": "1800",
        "VIS_NIGHT": "800",
        "TURNRATE": "0.6",
        "COLLISION": "24",
        "HP_SEC": "2.15",
        "LEGS": "2"
    },
    {
        "id": 113,
        "STR": "19",
        "STR_GAIN": "2.1",
        "STR_30": "79.9",
        "AGI": "24",
        "AGI_GAIN": "2.8",
        "AGI_30": "105.2",
        "INT": "19",
        "INT_GAIN": "1.8",
        "INT_30": "71.2",
        "TOTAL": "62",
        "TOTAL_GAIN": "6.7",
        "TOTAL_30": "256.3",
        "MS": "280",
        "ARMOR": "4",
        "DMG_MIN": "46",
        "DMG_MAX": "49",
        "RANGE": "450",
        "ATTACKSPEED": "115",
        "BAT": "1.7",
        "ATK_PT": "0.3",
        "ATK_BS": "0.7",
        "VIS_DAY": "1800",
        "VIS_NIGHT": "800",
        "TURNRATE": "0.6",
        "COLLISION": "24",
        "HP_SEC": "2.15",
        "LEGS": "0"
    },
    {
        "id": 114,
        "STR": "21",
        "STR_GAIN": "2.4",
        "STR_30": "90.6",
        "AGI": "21",
        "AGI_GAIN": "2.7",
        "AGI_30": "99.3",
        "INT": "17",
        "INT_GAIN": "2.0",
        "INT_30": "75",
        "TOTAL": "59",
        "TOTAL_GAIN": "7.1",
        "TOTAL_30": "264.9",
        "MS": "275",
        "ARMOR": "1.5",
        "DMG_MIN": "48",
        "DMG_MAX": "50",
        "RANGE": "575",
        "ATTACKSPEED": "120",
        "BAT": "1.7",
        "ATK_PT": "0.33",
        "ATK_BS": "1",
        "VIS_DAY": "1800",
        "VIS_NIGHT": "800",
        "TURNRATE": "0.6",
        "COLLISION": "24",
        "HP_SEC": "2.35",
        "LEGS": "0"
    },
    {
        "id": 115,
        "STR": "22",
        "STR_GAIN": "2.8",
        "STR_30": "103.2",
        "AGI": "11",
        "AGI_GAIN": "1.3",
        "AGI_30": "48.7",
        "INT": "22",
        "INT_GAIN": "2.9",
        "INT_30": "106.1",
        "TOTAL": "55",
        "TOTAL_GAIN": "7.0",
        "TOTAL_30": "258",
        "MS": "285",
        "ARMOR": "0.83",
        "DMG_MIN": "45",
        "DMG_MAX": "55",
        "RANGE": "600",
        "ATTACKSPEED": "110",
        "BAT": "1.7",
        "ATK_PT": "0.4",
        "ATK_BS": "0.54",
        "VIS_DAY": "1800",
        "VIS_NIGHT": "800",
        "TURNRATE": "0.6",
        "COLLISION": "24",
        "HP_SEC": "2.45",
        "LEGS": "2"
    },
    {
        "id": 116,
        "STR": "22",
        "STR_GAIN": "2.6",
        "STR_30": "97.4",
        "AGI": "19",
        "AGI_GAIN": "2.2",
        "AGI_30": "82.8",
        "INT": "24",
        "INT_GAIN": "3.1",
        "INT_30": "113.9",
        "TOTAL": "65",
        "TOTAL_GAIN": "7.9",
        "TOTAL_30": "294.1",
        "MS": "295",
        "ARMOR": "2.17",
        "DMG_MIN": "54",
        "DMG_MAX": "58",
        "RANGE": "200",
        "ATTACKSPEED": "100",
        "BAT": "1.7",
        "ATK_PT": "0.35",
        "ATK_BS": "0.78",
        "VIS_DAY": "1800",
        "VIS_NIGHT": "800",
        "TURNRATE": "0.7",
        "COLLISION": "24",
        "HP_SEC": "2.45",
        "LEGS": "2"
    },
    {
        "id": 117,
        "STR": "24",
        "STR_GAIN": "3.0",
        "STR_30": "111",
        "AGI": "10",
        "AGI_GAIN": "1.0",
        "AGI_30": "39",
        "INT": "25",
        "INT_GAIN": "3.1",
        "INT_30": "114.9",
        "TOTAL": "59",
        "TOTAL_GAIN": "7.1",
        "TOTAL_30": "264.9",
        "MS": "290",
        "ARMOR": "2.67",
        "DMG_MIN": "49",
        "DMG_MAX": "59",
        "RANGE": "600",
        "ATTACKSPEED": "100",
        "BAT": "1.7",
        "ATK_PT": "0.3",
        "ATK_BS": "0.3",
        "VIS_DAY": "1800",
        "VIS_NIGHT": "800",
        "TURNRATE": "0.6",
        "COLLISION": "24",
        "HP_SEC": "2.65",
        "LEGS": "2"
    },
    {
        "id": 118,
        "STR": "16",
        "STR_GAIN": "2.0",
        "STR_30": "74",
        "AGI": "17",
        "AGI_GAIN": "3.1",
        "AGI_30": "106.9",
        "INT": "20",
        "INT_GAIN": "2.0",
        "INT_30": "78",
        "TOTAL": "53",
        "TOTAL_GAIN": "7.1",
        "TOTAL_30": "258.9",
        "MS": "275",
        "ARMOR": "2.83",
        "DMG_MIN": "54",
        "DMG_MAX": "60",
        "RANGE": "425",
        "ATTACKSPEED": "120",
        "BAT": "1.8",
        "ATK_PT": "0.55",
        "ATK_BS": "0.36",
        "VIS_DAY": "1800",
        "VIS_NIGHT": "800",
        "TURNRATE": "0.6",
        "COLLISION": "24",
        "HP_SEC": "2.85",
        "LEGS": "4"
    },
    {
        "id": 119,
        "STR": "18",
        "STR_GAIN": "3.0",
        "STR_30": "105",
        "AGI": "17",
        "AGI_GAIN": "1.4",
        "AGI_30": "57.6",
        "INT": "18",
        "INT_GAIN": "3.6",
        "INT_30": "122.4",
        "TOTAL": "53",
        "TOTAL_GAIN": "8.0",
        "TOTAL_30": "285",
        "MS": "290",
        "ARMOR": "1.83",
        "DMG_MIN": "42",
        "DMG_MAX": "54",
        "RANGE": "600",
        "ATTACKSPEED": "100",
        "BAT": "1.5",
        "ATK_PT": "0.4",
        "ATK_BS": "0.3",
        "VIS_DAY": "1800",
        "VIS_NIGHT": "800",
        "TURNRATE": "0.8",
        "COLLISION": "24",
        "HP_SEC": "2.05",
        "LEGS": "2"
    },
    {
        "id": 120,
        "STR": "24",
        "STR_GAIN": "2.6",
        "STR_30": "99.4",
        "AGI": "16",
        "AGI_GAIN": "1.7",
        "AGI_30": "65.3",
        "INT": "26",
        "INT_GAIN": "3.6",
        "INT_30": "130.4",
        "TOTAL": "66",
        "TOTAL_GAIN": "7.9",
        "TOTAL_30": "295.1",
        "MS": "285",
        "ARMOR": "2.67",
        "DMG_MIN": "40",
        "DMG_MAX": "47",
        "RANGE": "425",
        "ATTACKSPEED": "100",
        "BAT": "1.7",
        "ATK_PT": "0.25",
        "ATK_BS": "0.8",
        "VIS_DAY": "1800",
        "VIS_NIGHT": "800",
        "TURNRATE": "0.6",
        "COLLISION": "24",
        "HP_SEC": "2.65",
        "LEGS": "2"
    },
    {
        "id": 121,
        "STR": "18",
        "STR_GAIN": "2.3",
        "STR_30": "84.7",
        "AGI": "13",
        "AGI_GAIN": "1.4",
        "AGI_30": "53.6",
        "INT": "22",
        "INT_GAIN": "3.3",
        "INT_30": "117.7",
        "TOTAL": "53",
        "TOTAL_GAIN": "7.0",
        "TOTAL_30": "256",
        "MS": "300",
        "ARMOR": "2.17",
        "DMG_MIN": "51",
        "DMG_MAX": "61",
        "RANGE": "600",
        "ATTACKSPEED": "100",
        "BAT": "1.7",
        "ATK_PT": "0.4",
        "ATK_BS": "0.5",
        "VIS_DAY": "1800",
        "VIS_NIGHT": "800",
        "TURNRATE": "0.6",
        "COLLISION": "24",
        "HP_SEC": "2.05",
        "LEGS": "2"
    },
    {
        "id": 122,
        "STR": "22",
        "STR_GAIN": "3.0",
        "STR_30": "109",
        "AGI": "16",
        "AGI_GAIN": "1.7",
        "AGI_30": "65.3",
        "INT": "18",
        "INT_GAIN": "1.6",
        "INT_30": "64.4",
        "TOTAL": "56",
        "TOTAL_GAIN": "6.3",
        "TOTAL_30": "238.7",
        "MS": "315",
        "ARMOR": "1.67",
        "DMG_MIN": "60",
        "DMG_MAX": "62",
        "RANGE": "150",
        "ATTACKSPEED": "100",
        "BAT": "1.7",
        "ATK_PT": "0.56",
        "ATK_BS": "0.44",
        "VIS_DAY": "1800",
        "VIS_NIGHT": "800",
        "TURNRATE": "0.6",
        "COLLISION": "24",
        "HP_SEC": "2.45",
        "LEGS": "2"
    },
    {
        "id": 123,
        "STR": "19",
        "STR_GAIN": "2.1",
        "STR_30": "79.9",
        "AGI": "11",
        "AGI_GAIN": "1.2",
        "AGI_30": "45.8",
        "INT": "22",
        "INT_GAIN": "3.3",
        "INT_30": "117.7",
        "TOTAL": "52",
        "TOTAL_GAIN": "6.6",
        "TOTAL_30": "243.4",
        "MS": "315",
        "ARMOR": "3.83",
        "DMG_MIN": "55",
        "DMG_MAX": "63",
        "RANGE": "380",
        "ATTACKSPEED": "100",
        "BAT": "1.7",
        "ATK_PT": "0.35",
        "ATK_BS": "0.55",
        "VIS_DAY": "1800",
        "VIS_NIGHT": "800",
        "TURNRATE": "0.6",
        "COLLISION": "24",
        "HP_SEC": "2.15",
        "LEGS": "2"
    }
]